[
  {
    "id": 1,
    "start": "2010-01-27",
    "content": "Rの基礎・統計学の基礎",
    "title": "TokyoR#01",
    "misc": "https://web.archive.org/web/20150918220709/https://atnd.org/events/2746"
  },
  {
    "id": 2,
    "start": "2010-02-24",
    "content": "Rで機械学習パッケージを試す(仮)",
    "title": "TokyoR#02LT",
    "misc": "https://web.archive.org/web/20150908113550/https://atnd.org/events/3054"
  },
  {
    "id": 3,
    "start": "2010-02-24",
    "content": "半導体と統計と私(仮)",
    "title": "TokyoR#02LT",
    "misc": "https://web.archive.org/web/20150908113550/https://atnd.org/events/3054"
  },
  {
    "id": 4,
    "start": "2010-04-24",
    "content": "Rによるやさしい統計学10章~14章",
    "title": "TokyoR#04",
    "misc": "https://web.archive.org/web/20150908143512/https://atnd.org/events/3930"
  },
  {
    "id": 5,
    "start": "2010-04-24",
    "content": "Rでカルマンフィルタ",
    "title": "TokyoR#04",
    "misc": "https://web.archive.org/web/20150908143512/https://atnd.org/events/3930"
  },
  {
    "id": 6,
    "start": "2010-04-24",
    "content": "財布にやさしいRを使ったデータマイニング",
    "title": "TokyoR#04",
    "misc": "https://web.archive.org/web/20150908143512/https://atnd.org/events/3930"
  },
  {
    "id": 7,
    "start": "2010-04-24",
    "content": "Value at Risk の紹介",
    "title": "TokyoR#04",
    "misc": "https://web.archive.org/web/20150908143512/https://atnd.org/events/3930"
  },
  {
    "id": 8,
    "start": "2010-04-24",
    "content": "R言語による時系列分析",
    "title": "TokyoR#04",
    "misc": "https://web.archive.org/web/20150908143512/https://atnd.org/events/3930"
  },
  {
    "id": 9,
    "start": "2010-04-24",
    "content": "分散分析",
    "title": "TokyoR#03",
    "misc": "https://web.archive.org/web/20150908114631/https://atnd.org/events/3454"
  },
  {
    "id": 10,
    "start": "2010-04-24",
    "content": "Optimization in R",
    "title": "TokyoR#03",
    "misc": "https://web.archive.org/web/20150908114631/https://atnd.org/events/3454"
  },
  {
    "id": 11,
    "start": "2010-04-24",
    "content": "プロセス、リソース、グラフと統計解析 -Unified graph representation of processes for scheduling with flexible resource assignment -",
    "title": "TokyoR#03",
    "misc": "https://web.archive.org/web/20150908114631/https://atnd.org/events/3454"
  },
  {
    "id": 12,
    "start": "2010-04-24",
    "content": "RFinanceYJを使ってみた",
    "title": "TokyoR#03LT",
    "misc": "https://web.archive.org/web/20150908114631/https://atnd.org/events/3454"
  },
  {
    "id": 13,
    "start": "2010-04-24",
    "content": "RとDBMS",
    "title": "TokyoR#03LT",
    "misc": "https://web.archive.org/web/20150908114631/https://atnd.org/events/3454"
  },
  {
    "id": 14,
    "start": "2010-04-24",
    "content": "25年前のS事情",
    "title": "TokyoR#03LT",
    "misc": "https://web.archive.org/web/20150908114631/https://atnd.org/events/3454"
  },
  {
    "id": 15,
    "start": "2010-05-22",
    "content": "Rによるやさしい統計学 : 第15章 回帰分析",
    "title": "TokyoR#05",
    "misc": "https://web.archive.org/web/20150908141738/https://atnd.org/events/4468"
  },
  {
    "id": 16,
    "start": "2010-05-22",
    "content": "人口統計データの分析手法の紹介",
    "title": "TokyoR#05",
    "misc": "https://web.archive.org/web/20150908141738/https://atnd.org/events/4468"
  },
  {
    "id": 17,
    "start": "2010-05-22",
    "content": "R言語による アソシエーション分析 - 組合せ・事象の規則を解明する -",
    "title": "TokyoR#05",
    "misc": "https://web.archive.org/web/20150908141738/https://atnd.org/events/4468"
  },
  {
    "id": 18,
    "start": "2010-05-22",
    "content": "RとWeb API (仮)",
    "title": "TokyoR#05",
    "misc": "https://web.archive.org/web/20150908141738/https://atnd.org/events/4468"
  },
  {
    "id": 19,
    "start": "2010-06-26",
    "content": "Rによるやさしい統計学 第16章 : 因子分析",
    "title": "TokyoR#06",
    "misc": "https://web.archive.org/web/20150918220519/https://atnd.org/events/5441"
  },
  {
    "id": 20,
    "start": "2010-06-26",
    "content": "ggplot2できれいなグラフ",
    "title": "TokyoR#06",
    "misc": "https://web.archive.org/web/20150918220519/https://atnd.org/events/5441"
  },
  {
    "id": 21,
    "start": "2010-06-26",
    "content": "Rで学ぶ金融工学入門 ~現代ポートフォリオ理論編~",
    "title": "TokyoR#06",
    "misc": "https://web.archive.org/web/20150918220519/https://atnd.org/events/5441"
  },
  {
    "id": 22,
    "start": "2010-06-26",
    "content": "金融工学入門 ~Rで確率微分方程式~",
    "title": "TokyoR#06",
    "misc": "https://web.archive.org/web/20150918220519/https://atnd.org/events/5441"
  },
  {
    "id": 23,
    "start": "2010-06-26",
    "content": "Y!ファイナンス非公式ガイド(仮)",
    "title": "TokyoR#06",
    "misc": "https://web.archive.org/web/20150918220519/https://atnd.org/events/5441"
  },
  {
    "id": 24,
    "start": "2010-07-24",
    "content": "Rによるやさしい統計学 第17章 : 共分散構造分析",
    "title": "TokyoR#07",
    "misc": "https://web.archive.org/web/20150915163757/https://atnd.org/events/6439"
  },
  {
    "id": 25,
    "start": "2010-07-24",
    "content": "PythonとR",
    "title": "TokyoR#07",
    "misc": "https://web.archive.org/web/20150915163757/https://atnd.org/events/6439"
  },
  {
    "id": 26,
    "start": "2010-07-24",
    "content": "R Language Definition案内~Rでハマったときのために~",
    "title": "TokyoR#07",
    "misc": "https://web.archive.org/web/20150915163757/https://atnd.org/events/6439"
  },
  {
    "id": 27,
    "start": "2010-07-24",
    "content": "Rで麻雀",
    "title": "TokyoR#07",
    "misc": "https://web.archive.org/web/20150915163757/https://atnd.org/events/6439"
  },
  {
    "id": 28,
    "start": "2010-07-24",
    "content": "RとC,C++の連携",
    "title": "TokyoR#07",
    "misc": "https://web.archive.org/web/20150915163757/https://atnd.org/events/6439"
  },
  {
    "id": 29,
    "start": "2010-07-24",
    "content": "10分で分かるRパッケージの作り方",
    "title": "TokyoR#07",
    "misc": "https://web.archive.org/web/20150915163757/https://atnd.org/events/6439"
  },
  {
    "id": 30,
    "start": "2010-08-28",
    "content": "Rによるデータサイエンス第II部 第3章 対応分析",
    "title": "TokyoR#08",
    "misc": "https://web.archive.org/web/20150918220838/https://atnd.org/events/7280"
  },
  {
    "id": 31,
    "start": "2010-08-28",
    "content": "ブランド・ポジショニングの分析",
    "title": "TokyoR#08",
    "misc": "https://web.archive.org/web/20150918220838/https://atnd.org/events/7280"
  },
  {
    "id": 32,
    "start": "2010-08-28",
    "content": "RでMapReduce",
    "title": "TokyoR#08",
    "misc": "https://web.archive.org/web/20150918220838/https://atnd.org/events/7280"
  },
  {
    "id": 33,
    "start": "2010-08-28",
    "content": "Rのハラワタをちょっと見てみる",
    "title": "TokyoR#08",
    "misc": "https://web.archive.org/web/20150918220838/https://atnd.org/events/7280"
  },
  {
    "id": 34,
    "start": "2010-08-28",
    "content": "Rの海外サイトのご紹介(仮)",
    "title": "TokyoR#08",
    "misc": "https://web.archive.org/web/20150918220838/https://atnd.org/events/7280"
  },
  {
    "id": 35,
    "start": "2010-09-19",
    "content": "Rの失敗?環境と変数代入と遅延評価と~R Language Definition案内番外編~",
    "title": "TokyoR#09",
    "misc": "https://web.archive.org/web/20150910223634/https://atnd.org/events/7804"
  },
  {
    "id": 36,
    "start": "2010-09-19",
    "content": "Rによるデータサイエンス第II部 第4章 多次元尺度法",
    "title": "TokyoR#09",
    "misc": "https://web.archive.org/web/20150910223634/https://atnd.org/events/7804"
  },
  {
    "id": 37,
    "start": "2010-09-19",
    "content": "Rによる文書モデルの可視化 ~トピックモデル、ディリクレ分布、LDA",
    "title": "TokyoR#09",
    "misc": "https://web.archive.org/web/20150910223634/https://atnd.org/events/7804"
  },
  {
    "id": 38,
    "start": "2010-09-19",
    "content": "RExcelでの日本語利用",
    "title": "TokyoR#09",
    "misc": "https://web.archive.org/web/20150910223634/https://atnd.org/events/7804"
  },
  {
    "id": 39,
    "start": "2010-09-19",
    "content": "スマートに時系列を捌く方法",
    "title": "TokyoR#09",
    "misc": "https://web.archive.org/web/20150910223634/https://atnd.org/events/7804"
  },
  {
    "id": 40,
    "start": "2010-10-31",
    "content": "Rによるデータサイエンス第II部 第5章 クラスター分析",
    "title": "TokyoR#10",
    "misc": "https://web.archive.org/web/20150918220539/https://atnd.org/events/9177"
  },
  {
    "id": 41,
    "start": "2010-10-31",
    "content": "スマートに時系列を捌く方法 2",
    "title": "TokyoR#10",
    "misc": "https://web.archive.org/web/20150918220539/https://atnd.org/events/9177"
  },
  {
    "id": 42,
    "start": "2010-10-31",
    "content": "基本パッケージの描画機能について",
    "title": "TokyoR#10",
    "misc": "https://web.archive.org/web/20150918220539/https://atnd.org/events/9177"
  },
  {
    "id": 43,
    "start": "2010-10-31",
    "content": "Japan.Rについて",
    "title": "TokyoR#10",
    "misc": "https://web.archive.org/web/20150918220539/https://atnd.org/events/9177"
  },
  {
    "id": 44,
    "start": "2010-10-31",
    "content": "マルコフ連鎖モンテカルロ法入門-1",
    "title": "TokyoR#10",
    "misc": "https://web.archive.org/web/20150918220539/https://atnd.org/events/9177"
  },
  {
    "id": 45,
    "start": "2011-01-29",
    "content": "Rによるデータサイエンス第II部 第6章 自己組織化マップ",
    "title": "TokyoR#11",
    "misc": "https://web.archive.org/web/20150918220349/https://atnd.org/events/12062"
  },
  {
    "id": 46,
    "start": "2011-01-29",
    "content": "ggplot2:パッケージ製作者(Wickamさん)の話を聞いて",
    "title": "TokyoR#11",
    "misc": "https://web.archive.org/web/20150918220349/https://atnd.org/events/12062"
  },
  {
    "id": 47,
    "start": "2011-01-29",
    "content": "caretパッケージの紹介",
    "title": "TokyoR#11",
    "misc": "https://web.archive.org/web/20150918220349/https://atnd.org/events/12062"
  },
  {
    "id": 48,
    "start": "2011-01-29",
    "content": "RにおけるHPC 並列計算編",
    "title": "TokyoR#11",
    "misc": "https://web.archive.org/web/20150918220349/https://atnd.org/events/12062"
  },
  {
    "id": 49,
    "start": "2011-01-29",
    "content": "Rで始めるテキストマイニング",
    "title": "TokyoR#11",
    "misc": "https://web.archive.org/web/20150918220349/https://atnd.org/events/12062"
  },
  {
    "id": 50,
    "start": "2011-01-29",
    "content": "R言語による Random Forest 徹底入門",
    "title": "TokyoR#11",
    "misc": "https://web.archive.org/web/20150918220349/https://atnd.org/events/12062"
  },
  {
    "id": 51,
    "start": "2011-03-05",
    "content": "Rによる回帰分析入門",
    "title": "TokyoR#12",
    "misc": "https://web.archive.org/web/20150915160127/https://atnd.org/events/13335"
  },
  {
    "id": 52,
    "start": "2011-03-05",
    "content": "Rで学ぶデータサイエンス 5パターン認識 1章 判別能力の評価",
    "title": "TokyoR#12",
    "misc": "https://web.archive.org/web/20150915160127/https://atnd.org/events/13335"
  },
  {
    "id": 53,
    "start": "2011-03-05",
    "content": "Rで学ぶ回帰分析と単位根検定",
    "title": "TokyoR#12",
    "misc": "https://web.archive.org/web/20150915160127/https://atnd.org/events/13335"
  },
  {
    "id": 54,
    "start": "2011-03-05",
    "content": "RをSQLで操る",
    "title": "TokyoR#12",
    "misc": "https://web.archive.org/web/20150915160127/https://atnd.org/events/13335"
  },
  {
    "id": 55,
    "start": "2011-03-05",
    "content": "Rあんな時こんな時 ~いつか役立つ(かもしれない)Tips~",
    "title": "TokyoR#12",
    "misc": "https://web.archive.org/web/20150915160127/https://atnd.org/events/13335"
  },
  {
    "id": 56,
    "start": "2011-03-05",
    "content": "世界のR(仮)",
    "title": "TokyoR#12",
    "misc": "https://web.archive.org/web/20150915160127/https://atnd.org/events/13335"
  },
  {
    "id": 57,
    "start": "2011-04-29",
    "content": "線形判別分析",
    "title": "TokyoR#13",
    "misc": "https://web.archive.org/web/20150908115035/https://atnd.org/events/14967"
  },
  {
    "id": 58,
    "start": "2011-04-29",
    "content": "R と .NET Framework",
    "title": "TokyoR#13",
    "misc": "https://web.archive.org/web/20150908115035/https://atnd.org/events/14967"
  },
  {
    "id": 59,
    "start": "2011-04-29",
    "content": "Rで学ぶロバスト推定",
    "title": "TokyoR#13",
    "misc": "https://web.archive.org/web/20150908115035/https://atnd.org/events/14967"
  },
  {
    "id": 60,
    "start": "2011-04-29",
    "content": "Rで地理空間分析 地理データのとりあつかい",
    "title": "TokyoR#13",
    "misc": "https://web.archive.org/web/20150908115035/https://atnd.org/events/14967"
  },
  {
    "id": 61,
    "start": "2011-04-29",
    "content": "YjdnJlpの紹介とか",
    "title": "TokyoR#13",
    "misc": "https://web.archive.org/web/20150908115035/https://atnd.org/events/14967"
  },
  {
    "id": 62,
    "start": "2011-04-29",
    "content": "Rパッケージガイドブックの紹介",
    "title": "TokyoR#13",
    "misc": "https://web.archive.org/web/20150908115035/https://atnd.org/events/14967"
  },
  {
    "id": 63,
    "start": "2011-05-28",
    "content": "非線形判別の勉強をしてみました",
    "title": "TokyoR#14",
    "misc": "https://web.archive.org/web/20151029071605/https://atnd.org/events/16080"
  },
  {
    "id": 64,
    "start": "2011-05-28",
    "content": "Rが黄色い象に出会った",
    "title": "TokyoR#14",
    "misc": "https://web.archive.org/web/20151029071605/https://atnd.org/events/16080"
  },
  {
    "id": 65,
    "start": "2011-05-28",
    "content": "Rで学ぶデータサイエンス 5パターン認識 2章 K-平均法",
    "title": "TokyoR#14",
    "misc": "https://web.archive.org/web/20151029071605/https://atnd.org/events/16080"
  },
  {
    "id": 66,
    "start": "2011-05-28",
    "content": "Rでisomap",
    "title": "TokyoR#14",
    "misc": "https://web.archive.org/web/20151029071605/https://atnd.org/events/16080"
  },
  {
    "id": 67,
    "start": "2011-05-28",
    "content": "Rのコードをキレイに見せたい",
    "title": "TokyoR#14",
    "misc": "https://web.archive.org/web/20151029071605/https://atnd.org/events/16080"
  },
  {
    "id": 68,
    "start": "2011-05-28",
    "content": "QC7つ道具",
    "title": "TokyoR#14",
    "misc": "https://web.archive.org/web/20151029071605/https://atnd.org/events/16080"
  },
  {
    "id": 69,
    "start": "2011-05-28",
    "content": "大規模データマイニングでのモデル探索手法:K-sample plot",
    "title": "TokyoR#14",
    "misc": "https://web.archive.org/web/20151029071605/https://atnd.org/events/16080"
  },
  {
    "id": 70,
    "start": "2011-07-02",
    "content": "テキスト第11章 生存分析",
    "title": "TokyoR#15",
    "misc": "https://web.archive.org/web/20150909222427/https://atnd.org/events/17410"
  },
  {
    "id": 71,
    "start": "2011-07-02",
    "content": "Rで学ぶデータサイエンス 第4章 混合正規分布モデル",
    "title": "TokyoR#15",
    "misc": "https://web.archive.org/web/20150909222427/https://atnd.org/events/17410"
  },
  {
    "id": 72,
    "start": "2011-07-02",
    "content": "xtsパッケージで時系列解析",
    "title": "TokyoR#15",
    "misc": "https://web.archive.org/web/20150909222427/https://atnd.org/events/17410"
  },
  {
    "id": 73,
    "start": "2011-07-02",
    "content": "Rによる異常検知入門(仮)",
    "title": "TokyoR#15",
    "misc": "https://web.archive.org/web/20150909222427/https://atnd.org/events/17410"
  },
  {
    "id": 74,
    "start": "2011-07-02",
    "content": "ggplot2とgoogleVisとhwriterでレポートを作る",
    "title": "TokyoR#15",
    "misc": "https://web.archive.org/web/20150909222427/https://atnd.org/events/17410"
  },
  {
    "id": 75,
    "start": "2011-08-27",
    "content": "Rで学ぶデータサイエンス5パターン認識 8,9k-近傍法、学習ベクトル量子化",
    "title": "TokyoR#16",
    "misc": "https://web.archive.org/web/20151022161112/https://atnd.org/events/19192"
  },
  {
    "id": 76,
    "start": "2011-08-27",
    "content": "Rを用いた地理的情報解析",
    "title": "TokyoR#16",
    "misc": "https://web.archive.org/web/20151022161112/https://atnd.org/events/19192"
  },
  {
    "id": 77,
    "start": "2011-08-27",
    "content": "Rデバッグあれこれ(仮)",
    "title": "TokyoR#16",
    "misc": "https://web.archive.org/web/20151022161112/https://atnd.org/events/19192"
  },
  {
    "id": 78,
    "start": "2011-08-27",
    "content": "Rで実験計画法",
    "title": "TokyoR#16",
    "misc": "https://web.archive.org/web/20151022161112/https://atnd.org/events/19192"
  },
  {
    "id": 79,
    "start": "2011-08-27",
    "content": "DICEWARS by R",
    "title": "TokyoR#16",
    "misc": "https://web.archive.org/web/20151022161112/https://atnd.org/events/19192"
  },
  {
    "id": 80,
    "start": "2011-08-27",
    "content": "Rで大規模データ解析",
    "title": "TokyoR#16",
    "misc": "https://web.archive.org/web/20151022161112/https://atnd.org/events/19192"
  },
  {
    "id": 81,
    "start": "2011-08-27",
    "content": "シリーズRで可視化#2 インフォグラフはじめました",
    "title": "TokyoR#16",
    "misc": "https://web.archive.org/web/20151022161112/https://atnd.org/events/19192"
  },
  {
    "id": 82,
    "start": "2011-08-27",
    "content": "異常行動検出入門 – 行動データ時系列のデータマイニング –",
    "title": "TokyoR#16",
    "misc": "https://web.archive.org/web/20151022161112/https://atnd.org/events/19192"
  },
  {
    "id": 83,
    "start": "2011-09-24",
    "content": "Rによるデータサイエンス第12章「時系列」",
    "title": "TokyoR#17",
    "misc": "https://web.archive.org/web/20151022165528/https://atnd.org/events/19835"
  },
  {
    "id": 84,
    "start": "2011-09-24",
    "content": "Rで解く最適化問題 – 線型計画問題編 –",
    "title": "TokyoR#17",
    "misc": "https://web.archive.org/web/20151022165528/https://atnd.org/events/19835"
  },
  {
    "id": 85,
    "start": "2011-09-24",
    "content": "近似ベイズ計算でカジュアルなベイズ推定",
    "title": "TokyoR#17",
    "misc": "https://web.archive.org/web/20151022165528/https://atnd.org/events/19835"
  },
  {
    "id": 86,
    "start": "2011-09-24",
    "content": "Rで学ぶ傾向スコア解析入門",
    "title": "TokyoR#17",
    "misc": "https://web.archive.org/web/20151022165528/https://atnd.org/events/19835"
  },
  {
    "id": 87,
    "start": "2011-09-24",
    "content": "サーバ異常検知入門",
    "title": "TokyoR#17",
    "misc": "https://web.archive.org/web/20151022165528/https://atnd.org/events/19835"
  },
  {
    "id": 88,
    "start": "2011-09-24",
    "content": "Rによる計量経済学入門",
    "title": "TokyoR#17",
    "misc": "https://web.archive.org/web/20151022165528/https://atnd.org/events/19835"
  },
  {
    "id": 89,
    "start": "2011-09-24",
    "content": "TokyoR等の軌跡",
    "title": "TokyoR#17LT",
    "misc": "https://web.archive.org/web/20151022165528/https://atnd.org/events/19835"
  },
  {
    "id": 90,
    "start": "2011-09-24",
    "content": "Rで富士山を描いてみた",
    "title": "TokyoR#17LT",
    "misc": "https://web.archive.org/web/20151022165528/https://atnd.org/events/19835"
  },
  {
    "id": 91,
    "start": "2011-10-22",
    "content": "はじめてのR",
    "title": "TokyoR#18",
    "misc": "https://web.archive.org/web/20150908130456/https://atnd.org/events/21050"
  },
  {
    "id": 92,
    "start": "2011-10-22",
    "content": "XLConnectで快適なエクセルライフのご提案",
    "title": "TokyoR#18",
    "misc": "https://web.archive.org/web/20150908130456/https://atnd.org/events/21050"
  },
  {
    "id": 93,
    "start": "2011-10-22",
    "content": "Rによるデータサイエンス第13章「樹木モデル」",
    "title": "TokyoR#18",
    "misc": "https://web.archive.org/web/20150908130456/https://atnd.org/events/21050"
  },
  {
    "id": 94,
    "start": "2011-10-22",
    "content": "Rで学ぶ現代ポートフォリオ理論",
    "title": "TokyoR#18",
    "misc": "https://web.archive.org/web/20150908130456/https://atnd.org/events/21050"
  },
  {
    "id": 95,
    "start": "2011-10-22",
    "content": "部分的最小二乗法",
    "title": "TokyoR#18",
    "misc": "https://web.archive.org/web/20150908130456/https://atnd.org/events/21050"
  },
  {
    "id": 96,
    "start": "2011-10-22",
    "content": "最適化アレ コレ ソレ",
    "title": "TokyoR#18",
    "misc": "https://web.archive.org/web/20150908130456/https://atnd.org/events/21050"
  },
  {
    "id": 97,
    "start": "2011-10-22",
    "content": "RHadoopの紹介",
    "title": "TokyoR#18",
    "misc": "https://web.archive.org/web/20150908130456/https://atnd.org/events/21050"
  },
  {
    "id": 98,
    "start": "2011-10-22",
    "content": "Rで計量経済(操作変数を使ったバイアス調整)",
    "title": "TokyoR#18LT",
    "misc": "https://web.archive.org/web/20150908130456/https://atnd.org/events/21050"
  },
  {
    "id": 99,
    "start": "2011-11-19",
    "content": "Rによるデータサイエンス 第14章 ニューラルネットワーク",
    "title": "TokyoR#19",
    "misc": "https://web.archive.org/web/20151022171044/https://atnd.org/events/22138"
  },
  {
    "id": 100,
    "start": "2011-11-19",
    "content": "デリバティブについて",
    "title": "TokyoR#19",
    "misc": "https://web.archive.org/web/20151022171044/https://atnd.org/events/22138"
  },
  {
    "id": 101,
    "start": "2011-11-19",
    "content": "Rで色々やってみました",
    "title": "TokyoR#19",
    "misc": "https://web.archive.org/web/20151022171044/https://atnd.org/events/22138"
  },
  {
    "id": 102,
    "start": "2011-11-19",
    "content": "複雑ネットワーク徹底入門",
    "title": "TokyoR#19",
    "misc": "https://web.archive.org/web/20151022171044/https://atnd.org/events/22138"
  },
  {
    "id": 103,
    "start": "2011-11-19",
    "content": "R で解く FizzBuzz 問題",
    "title": "TokyoR#19LT",
    "misc": "https://web.archive.org/web/20151022171044/https://atnd.org/events/22138"
  },
  {
    "id": 104,
    "start": "2011-11-19",
    "content": "RでGPU使ってみるわ~",
    "title": "TokyoR#19LT",
    "misc": "https://web.archive.org/web/20151022171044/https://atnd.org/events/22138"
  },
  {
    "id": 105,
    "start": "2012-01-28",
    "content": "animationパッケージのご紹介(仮)",
    "title": "TokyoR#20",
    "misc": "https://web.archive.org/web/20151022165111/https://atnd.org/events/24629"
  },
  {
    "id": 106,
    "start": "2012-01-28",
    "content": "ポアソン分布と指数分布のいけない関係",
    "title": "TokyoR#20",
    "misc": "https://web.archive.org/web/20151022165111/https://atnd.org/events/24629"
  },
  {
    "id": 107,
    "start": "2012-01-28",
    "content": "均衡データのクラス分類(仮)",
    "title": "TokyoR#20",
    "misc": "https://web.archive.org/web/20151022165111/https://atnd.org/events/24629"
  },
  {
    "id": 108,
    "start": "2012-01-28",
    "content": "Rでマンデルブロ集合",
    "title": "TokyoR#20LT",
    "misc": "https://web.archive.org/web/20151022165111/https://atnd.org/events/24629"
  },
  {
    "id": 109,
    "start": "2012-01-28",
    "content": "お詫びとお知らせ",
    "title": "TokyoR#20LT",
    "misc": "https://web.archive.org/web/20151022165111/https://atnd.org/events/24629"
  },
  {
    "id": 110,
    "start": "2012-01-28",
    "content": "Rによるデータサイエンス 第15章 カーネル法とサポートベクターマシン",
    "title": "TokyoR#20LT",
    "misc": "https://web.archive.org/web/20151022165111/https://atnd.org/events/24629"
  },
  {
    "id": 111,
    "start": "2012-03-10",
    "content": "続・はじめてのR",
    "title": "TokyoR#21",
    "misc": "https://web.archive.org/web/20150925194756/https://atnd.org/events/24811"
  },
  {
    "id": 112,
    "start": "2012-03-10",
    "content": "Rによるデータサイエンス第16章 集団学習",
    "title": "TokyoR#21",
    "misc": "https://web.archive.org/web/20150925194756/https://atnd.org/events/24811"
  },
  {
    "id": 113,
    "start": "2012-03-10",
    "content": "観察データのバイアス調整",
    "title": "TokyoR#21",
    "misc": "https://web.archive.org/web/20150925194756/https://atnd.org/events/24811"
  },
  {
    "id": 114,
    "start": "2012-03-10",
    "content": "RでGARCHモデル",
    "title": "TokyoR#21",
    "misc": "https://web.archive.org/web/20150925194756/https://atnd.org/events/24811"
  },
  {
    "id": 115,
    "start": "2012-03-10",
    "content": "テキストマイニングで見る『機動戦士ガンダム』",
    "title": "TokyoR#21",
    "misc": "https://web.archive.org/web/20150925194756/https://atnd.org/events/24811"
  },
  {
    "id": 116,
    "start": "2012-03-10",
    "content": "Uplift Modelling",
    "title": "TokyoR#21",
    "misc": "https://web.archive.org/web/20150925194756/https://atnd.org/events/24811"
  },
  {
    "id": 117,
    "start": "2012-03-10",
    "content": "RでPSM分析",
    "title": "TokyoR#21LT",
    "misc": "https://web.archive.org/web/20150925194756/https://atnd.org/events/24811"
  },
  {
    "id": 118,
    "start": "2012-03-10",
    "content": "オタク的な標準偏差",
    "title": "TokyoR#21LT",
    "misc": "https://web.archive.org/web/20150925194756/https://atnd.org/events/24811"
  },
  {
    "id": 119,
    "start": "2012-03-10",
    "content": "菩薩でもわかる!Rで動かすExcelアドインの作り方",
    "title": "TokyoR#21LT",
    "misc": "https://web.archive.org/web/20150925194756/https://atnd.org/events/24811"
  },
  {
    "id": 120,
    "start": "2012-03-10",
    "content": "二部グラフを使ったソーシャルネットワーク",
    "title": "TokyoR#21LT",
    "misc": "https://web.archive.org/web/20150925194756/https://atnd.org/events/24811"
  },
  {
    "id": 121,
    "start": "2012-04-28",
    "content": "パターン認識",
    "title": "TokyoR#22",
    "misc": "https://web.archive.org/web/20150912010949/https://atnd.org/events/26386"
  },
  {
    "id": 122,
    "start": "2012-04-28",
    "content": "アソシエーション分析",
    "title": "TokyoR#22",
    "misc": "https://web.archive.org/web/20150912010949/https://atnd.org/events/26386"
  },
  {
    "id": 123,
    "start": "2012-04-28",
    "content": "Rで実験計画法中編",
    "title": "TokyoR#22",
    "misc": "https://web.archive.org/web/20150912010949/https://atnd.org/events/26386"
  },
  {
    "id": 124,
    "start": "2012-04-28",
    "content": "選択バイアス入門",
    "title": "TokyoR#22",
    "misc": "https://web.archive.org/web/20150912010949/https://atnd.org/events/26386"
  },
  {
    "id": 125,
    "start": "2012-04-28",
    "content": "どっち使う?分散の式",
    "title": "TokyoR#22LT",
    "misc": "https://web.archive.org/web/20150912010949/https://atnd.org/events/26386"
  },
  {
    "id": 126,
    "start": "2012-04-28",
    "content": "ガチャとマルコフ連鎖",
    "title": "TokyoR#22LT",
    "misc": "https://web.archive.org/web/20150912010949/https://atnd.org/events/26386"
  },
  {
    "id": 127,
    "start": "2012-04-28",
    "content": "RとProcessingの連携",
    "title": "TokyoR#22LT",
    "misc": "https://web.archive.org/web/20150912010949/https://atnd.org/events/26386"
  },
  {
    "id": 128,
    "start": "2012-04-28",
    "content": "MKLのshogun-toolboxをRで使う",
    "title": "TokyoR#22LT",
    "misc": "https://web.archive.org/web/20150912010949/https://atnd.org/events/26386"
  },
  {
    "id": 129,
    "start": "2012-04-28",
    "content": "Rで音声合成やってみた",
    "title": "TokyoR#22LT",
    "misc": "https://web.archive.org/web/20150912010949/https://atnd.org/events/26386"
  },
  {
    "id": 130,
    "start": "2012-04-28",
    "content": "らくがき!",
    "title": "TokyoR#22LT",
    "misc": "https://web.archive.org/web/20150912010949/https://atnd.org/events/26386"
  },
  {
    "id": 131,
    "start": "2012-05-26",
    "content": "そういえば,Rとは何だったか思い出してみる",
    "title": "TokyoR#23",
    "misc": "https://web.archive.org/web/20150918220441/https://atnd.org/events/28416"
  },
  {
    "id": 132,
    "start": "2012-05-26",
    "content": "Rによるやさしい統計学 2nd Time 第一章辺りでー!二章、三章は余力あれば",
    "title": "TokyoR#23",
    "misc": "https://web.archive.org/web/20150918220441/https://atnd.org/events/28416"
  },
  {
    "id": 133,
    "start": "2012-05-26",
    "content": "最近、混合効果モデルに興味をもった私がとりいそぎやったこと",
    "title": "TokyoR#23",
    "misc": "https://web.archive.org/web/20150918220441/https://atnd.org/events/28416"
  },
  {
    "id": 134,
    "start": "2012-05-26",
    "content": "Rでデータマイニング 〜第二章〜",
    "title": "TokyoR#23",
    "misc": "https://web.archive.org/web/20150918220441/https://atnd.org/events/28416"
  },
  {
    "id": 135,
    "start": "2012-05-26",
    "content": "傾向スコア解析とUplift Modelling",
    "title": "TokyoR#23",
    "misc": "https://web.archive.org/web/20150918220441/https://atnd.org/events/28416"
  },
  {
    "id": 136,
    "start": "2012-05-26",
    "content": "CRAN Task Views でパッケージ管理",
    "title": "TokyoR#23LT",
    "misc": "https://web.archive.org/web/20150918220441/https://atnd.org/events/28416"
  },
  {
    "id": 137,
    "start": "2012-05-26",
    "content": "Rでネットワーク分析勉強会のご紹介",
    "title": "TokyoR#23LT",
    "misc": "https://web.archive.org/web/20150918220441/https://atnd.org/events/28416"
  },
  {
    "id": 138,
    "start": "2012-05-26",
    "content": "あるおっさんが記録し続けた データを使えば人生一発逆転か?",
    "title": "TokyoR#23LT",
    "misc": "https://web.archive.org/web/20150918220441/https://atnd.org/events/28416"
  },
  {
    "id": 139,
    "start": "2012-05-26",
    "content": "Rで回すROKURO 2.0",
    "title": "TokyoR#23LT",
    "misc": "https://web.archive.org/web/20150918220441/https://atnd.org/events/28416"
  },
  {
    "id": 140,
    "start": "2012-07-07",
    "content": "Rによるやさしい統計学 第2,3章",
    "title": "TokyoR#24",
    "misc": "https://web.archive.org/web/20150910225909/https://atnd.org/events/29541"
  },
  {
    "id": 141,
    "start": "2012-07-07",
    "content": "RでReproducible Research",
    "title": "TokyoR#24",
    "misc": "https://web.archive.org/web/20150910225909/https://atnd.org/events/29541"
  },
  {
    "id": 142,
    "start": "2012-07-07",
    "content": "Rでデータマイニング〜サンプリングデータのケース〜",
    "title": "TokyoR#24",
    "misc": "https://web.archive.org/web/20150910225909/https://atnd.org/events/29541"
  },
  {
    "id": 143,
    "start": "2012-07-07",
    "content": "データベースのお話し",
    "title": "TokyoR#24",
    "misc": "https://web.archive.org/web/20150910225909/https://atnd.org/events/29541"
  },
  {
    "id": 144,
    "start": "2012-07-07",
    "content": "パフォーマンス R vs C#",
    "title": "TokyoR#24",
    "misc": "https://web.archive.org/web/20150910225909/https://atnd.org/events/29541"
  },
  {
    "id": 145,
    "start": "2012-07-07",
    "content": "マーケティングの統計分析 – 4.2 プロモーション –",
    "title": "TokyoR#24",
    "misc": "https://web.archive.org/web/20150910225909/https://atnd.org/events/29541"
  },
  {
    "id": 146,
    "start": "2012-08-04",
    "content": "Rによるやさしい統計学第4章 母集団と標本",
    "title": "TokyoR#25",
    "misc": "https://web.archive.org/web/20150919172719/https://atnd.org/events/30646"
  },
  {
    "id": 147,
    "start": "2012-08-04",
    "content": "セキュリティ関係の何か",
    "title": "TokyoR#25",
    "misc": "https://web.archive.org/web/20150919172719/https://atnd.org/events/30646"
  },
  {
    "id": 148,
    "start": "2012-08-04",
    "content": "Rで学ぶ 『倒産確率推定』",
    "title": "TokyoR#25",
    "misc": "https://web.archive.org/web/20150919172719/https://atnd.org/events/30646"
  },
  {
    "id": 149,
    "start": "2012-08-04",
    "content": "びっぐでぇた解析環境あ~る~主としてRevolution Rのご紹介~",
    "title": "TokyoR#25",
    "misc": "https://web.archive.org/web/20150919172719/https://atnd.org/events/30646"
  },
  {
    "id": 150,
    "start": "2012-08-04",
    "content": "ダイナミックOLS",
    "title": "TokyoR#25LT",
    "misc": "https://web.archive.org/web/20150919172719/https://atnd.org/events/30646"
  },
  {
    "id": 151,
    "start": "2012-08-04",
    "content": "Rの乱数でいろいろ乱数を作る",
    "title": "TokyoR#25LT",
    "misc": "https://web.archive.org/web/20150919172719/https://atnd.org/events/30646"
  },
  {
    "id": 152,
    "start": "2012-08-04",
    "content": "RStudioで始めるTシャツ祭り",
    "title": "TokyoR#25LT",
    "misc": "https://web.archive.org/web/20150919172719/https://atnd.org/events/30646"
  },
  {
    "id": 153,
    "start": "2012-10-20",
    "content": "サンプリング方法とそれに基いた分析(仮)",
    "title": "TokyoR#27",
    "misc": "https://web.archive.org/web/20140911184755/https://atnd.org/events/32714"
  },
  {
    "id": 154,
    "start": "2012-10-20",
    "content": "R de 学ぶ逆変換法",
    "title": "TokyoR#27",
    "misc": "https://web.archive.org/web/20140911184755/https://atnd.org/events/32714"
  },
  {
    "id": 155,
    "start": "2012-10-20",
    "content": "ggplot2に入門してみた",
    "title": "TokyoR#27",
    "misc": "https://web.archive.org/web/20140911184755/https://atnd.org/events/32714"
  },
  {
    "id": 156,
    "start": "2012-10-20",
    "content": "僕の考える真の可愛い女性について(仮)",
    "title": "TokyoR#27",
    "misc": "https://web.archive.org/web/20140911184755/https://atnd.org/events/32714"
  },
  {
    "id": 157,
    "start": "2012-10-20",
    "content": "Rでカジュアルに異常検知 ChangeAnomalyDetectionパッケージ",
    "title": "TokyoR#27",
    "misc": "https://web.archive.org/web/20140911184755/https://atnd.org/events/32714"
  },
  {
    "id": 158,
    "start": "2012-10-20",
    "content": "R Advent Calendar 2012 やります",
    "title": "TokyoR#27LT",
    "misc": "https://web.archive.org/web/20140911184755/https://atnd.org/events/32714"
  },
  {
    "id": 159,
    "start": "2013-01-26",
    "content": "Rによるやさしい統計学 第6章 2つの平均値を比較する",
    "title": "TokyoR#28",
    "misc": "https://web.archive.org/web/20150909224333/https://atnd.org/events/35764"
  },
  {
    "id": 160,
    "start": "2013-01-26",
    "content": "初心者セッション2 Rでピボットテーブル",
    "title": "TokyoR#28",
    "misc": "https://web.archive.org/web/20150909224333/https://atnd.org/events/35764"
  },
  {
    "id": 161,
    "start": "2013-01-26",
    "content": "シリーズ前処理2013:欠測データの補完",
    "title": "TokyoR#28",
    "misc": "https://web.archive.org/web/20150909224333/https://atnd.org/events/35764"
  },
  {
    "id": 162,
    "start": "2013-01-26",
    "content": "Rで行うブランド資産測定〜自由記述文章分析編〜",
    "title": "TokyoR#28",
    "misc": "https://web.archive.org/web/20150909224333/https://atnd.org/events/35764"
  },
  {
    "id": 163,
    "start": "2013-01-26",
    "content": "mboostパッケージについて",
    "title": "TokyoR#28",
    "misc": "https://web.archive.org/web/20150909224333/https://atnd.org/events/35764"
  },
  {
    "id": 164,
    "start": "2013-01-26",
    "content": "shinyはじめました",
    "title": "TokyoR#28",
    "misc": "https://web.archive.org/web/20150909224333/https://atnd.org/events/35764"
  },
  {
    "id": 165,
    "start": "2013-01-26",
    "content": "Rで階層ベイズモデル(仮)",
    "title": "TokyoR#28",
    "misc": "https://web.archive.org/web/20150909224333/https://atnd.org/events/35764"
  },
  {
    "id": 166,
    "start": "2013-01-26",
    "content": "標準偏差と不偏標準偏差とを母集団の大きさと標本の大きさとを変えて比較してみた",
    "title": "TokyoR#28LT",
    "misc": "https://web.archive.org/web/20150909224333/https://atnd.org/events/35764"
  },
  {
    "id": 167,
    "start": "2013-01-26",
    "content": "顔",
    "title": "TokyoR#28LT",
    "misc": "https://web.archive.org/web/20150909224333/https://atnd.org/events/35764"
  },
  {
    "id": 168,
    "start": "2013-01-26",
    "content": "アッシェンフェルターのワイン方程式",
    "title": "TokyoR#28LT",
    "misc": "https://web.archive.org/web/20150909224333/https://atnd.org/events/35764"
  },
  {
    "id": 169,
    "start": "2013-01-26",
    "content": "Rでレポートメール",
    "title": "TokyoR#28LT",
    "misc": "https://web.archive.org/web/20150909224333/https://atnd.org/events/35764"
  },
  {
    "id": 170,
    "start": "2013-02-23",
    "content": "Rによるやさしい統計学 第7章 分散分析",
    "title": "TokyoR#29",
    "misc": "https://web.archive.org/web/20151022161703/https://atnd.org/events/36417"
  },
  {
    "id": 171,
    "start": "2013-02-23",
    "content": "Rで始めるかもしれない顧客ベース分析",
    "title": "TokyoR#29",
    "misc": "https://web.archive.org/web/20151022161703/https://atnd.org/events/36417"
  },
  {
    "id": 172,
    "start": "2013-02-23",
    "content": "mboostパッケージについて",
    "title": "TokyoR#29",
    "misc": "https://web.archive.org/web/20151022161703/https://atnd.org/events/36417"
  },
  {
    "id": 173,
    "start": "2013-02-23",
    "content": "RでAHP",
    "title": "TokyoR#29",
    "misc": "https://web.archive.org/web/20151022161703/https://atnd.org/events/36417"
  },
  {
    "id": 174,
    "start": "2013-02-23",
    "content": "シリーズ前処理2013:外れ値(仮)",
    "title": "TokyoR#29",
    "misc": "https://web.archive.org/web/20151022161703/https://atnd.org/events/36417"
  },
  {
    "id": 175,
    "start": "2013-02-23",
    "content": "ベイジアンネットワークによる推論モデルの構築",
    "title": "TokyoR#29",
    "misc": "https://web.archive.org/web/20151022161703/https://atnd.org/events/36417"
  },
  {
    "id": 176,
    "start": "2013-02-23",
    "content": "R@Qiita",
    "title": "TokyoR#29LT",
    "misc": "https://web.archive.org/web/20151022161703/https://atnd.org/events/36417"
  },
  {
    "id": 177,
    "start": "2013-02-23",
    "content": "RとC++と画像処理 (PARR2)",
    "title": "TokyoR#29LT",
    "misc": "https://web.archive.org/web/20151022161703/https://atnd.org/events/36417"
  },
  {
    "id": 178,
    "start": "2013-02-23",
    "content": "信号検出理論とR",
    "title": "TokyoR#29LT",
    "misc": "https://web.archive.org/web/20151022161703/https://atnd.org/events/36417"
  },
  {
    "id": 179,
    "start": "2013-02-23",
    "content": "Tokyo.R 白熱教室「これからのRcppの話をしよう」",
    "title": "TokyoR#29LT",
    "misc": "https://web.archive.org/web/20151022161703/https://atnd.org/events/36417"
  },
  {
    "id": 180,
    "start": "2013-02-23",
    "content": "Rのコーディングを勉強してみた",
    "title": "TokyoR#29LT",
    "misc": "https://web.archive.org/web/20151022161703/https://atnd.org/events/36417"
  },
  {
    "id": 181,
    "start": "2013-02-23",
    "content": "セイバーメトリクス",
    "title": "TokyoR#29LT",
    "misc": "https://web.archive.org/web/20151022161703/https://atnd.org/events/36417"
  },
  {
    "id": 182,
    "start": "2013-04-20",
    "content": "Rによるやさしい統計学 第7章 分散分析(後半)",
    "title": "TokyoR#30",
    "misc": "https://web.archive.org/web/20150908120616/https://atnd.org/events/38512"
  },
  {
    "id": 183,
    "start": "2013-04-20",
    "content": "協調フィルタリング入門",
    "title": "TokyoR#30",
    "misc": "https://web.archive.org/web/20150908120616/https://atnd.org/events/38512"
  },
  {
    "id": 184,
    "start": "2013-04-20",
    "content": "歴史を学んでR言語の未来を考える",
    "title": "TokyoR#30",
    "misc": "https://web.archive.org/web/20150908120616/https://atnd.org/events/38512"
  },
  {
    "id": 185,
    "start": "2013-04-20",
    "content": "Rでコンジョイント分析",
    "title": "TokyoR#30",
    "misc": "https://web.archive.org/web/20150908120616/https://atnd.org/events/38512"
  },
  {
    "id": 186,
    "start": "2013-04-20",
    "content": "plyrパッケージで君も前処理スタ☆",
    "title": "TokyoR#30",
    "misc": "https://web.archive.org/web/20150908120616/https://atnd.org/events/38512"
  },
  {
    "id": 187,
    "start": "2013-04-20",
    "content": "RとC++と画像処理 (PART3)",
    "title": "TokyoR#30LT",
    "misc": "https://web.archive.org/web/20150908120616/https://atnd.org/events/38512"
  },
  {
    "id": 188,
    "start": "2013-04-20",
    "content": ".NET で書いて R で実行",
    "title": "TokyoR#30LT",
    "misc": "https://web.archive.org/web/20150908120616/https://atnd.org/events/38512"
  },
  {
    "id": 189,
    "start": "2013-04-20",
    "content": "fluentdとR でお手軽ログ解析",
    "title": "TokyoR#30LT",
    "misc": "https://web.archive.org/web/20150908120616/https://atnd.org/events/38512"
  },
  {
    "id": 190,
    "start": "2013-04-20",
    "content": "R 3.0.0 is released!",
    "title": "TokyoR#30LT",
    "misc": "https://web.archive.org/web/20150908120616/https://atnd.org/events/38512"
  },
  {
    "id": 191,
    "start": "2013-04-20",
    "content": "RでSPARQL",
    "title": "TokyoR#30LT",
    "misc": "https://web.archive.org/web/20150908120616/https://atnd.org/events/38512"
  },
  {
    "id": 192,
    "start": "2013-04-20",
    "content": "R-3.0.0を使ってみてわかったn個のこと",
    "title": "TokyoR#30LT",
    "misc": "https://web.archive.org/web/20150908120616/https://atnd.org/events/38512"
  },
  {
    "id": 193,
    "start": "2013-06-01",
    "content": "Rによるやさしい統計学 第7章 分散分析(後半の後半)",
    "title": "TokyoR#31",
    "misc": "https://web.archive.org/web/20150908191002/https://atnd.org/events/38992"
  },
  {
    "id": 194,
    "start": "2013-06-01",
    "content": "中の人が語る seekR.jp の裏技(仮)",
    "title": "TokyoR#31",
    "misc": "https://web.archive.org/web/20150908191002/https://atnd.org/events/38992"
  },
  {
    "id": 195,
    "start": "2013-06-01",
    "content": "始めよう多変量解析~主成分分析編~",
    "title": "TokyoR#31",
    "misc": "https://web.archive.org/web/20150908191002/https://atnd.org/events/38992"
  },
  {
    "id": 196,
    "start": "2013-06-01",
    "content": "R言語で学ぶマーケティング分析 – 競争ポジショニング戦略 –",
    "title": "TokyoR#31",
    "misc": "https://web.archive.org/web/20150908191002/https://atnd.org/events/38992"
  },
  {
    "id": 197,
    "start": "2013-06-01",
    "content": "R による自然言語処理入門(仮)",
    "title": "TokyoR#31",
    "misc": "https://web.archive.org/web/20150908191002/https://atnd.org/events/38992"
  },
  {
    "id": 198,
    "start": "2013-06-01",
    "content": "RとPythonによるデータ解析入門",
    "title": "TokyoR#31",
    "misc": "https://web.archive.org/web/20150908191002/https://atnd.org/events/38992"
  },
  {
    "id": 199,
    "start": "2013-06-01",
    "content": "RでARIMAの話",
    "title": "TokyoR#31LT",
    "misc": "https://web.archive.org/web/20150908191002/https://atnd.org/events/38992"
  },
  {
    "id": 200,
    "start": "2013-06-01",
    "content": "rzmqで並列分散コンピューティング",
    "title": "TokyoR#31LT",
    "misc": "https://web.archive.org/web/20150908191002/https://atnd.org/events/38992"
  },
  {
    "id": 201,
    "start": "2013-06-01",
    "content": "可視化周辺の進化がヤヴァイ~rChartsを中心として~",
    "title": "TokyoR#31LT",
    "misc": "https://web.archive.org/web/20150908191002/https://atnd.org/events/38992"
  },
  {
    "id": 202,
    "start": "2013-06-01",
    "content": "ABテストと結果の検定",
    "title": "TokyoR#31LT",
    "misc": "https://web.archive.org/web/20150908191002/https://atnd.org/events/38992"
  },
  {
    "id": 203,
    "start": "2013-06-01",
    "content": "R で自然順ソートを実装してみた",
    "title": "TokyoR#31LT",
    "misc": "https://web.archive.org/web/20150908191002/https://atnd.org/events/38992"
  },
  {
    "id": 204,
    "start": "2013-07-20",
    "content": "平均から正規分布まで",
    "title": "TokyoR#32",
    "misc": "https://web.archive.org/web/20140911201225/https://atnd.org/events/40213"
  },
  {
    "id": 205,
    "start": "2013-07-20",
    "content": "実践で学ぶネットワーク分析",
    "title": "TokyoR#32",
    "misc": "https://web.archive.org/web/20140911201225/https://atnd.org/events/40213"
  },
  {
    "id": 206,
    "start": "2013-07-20",
    "content": "独立成分分析",
    "title": "TokyoR#32",
    "misc": "https://web.archive.org/web/20140911201225/https://atnd.org/events/40213"
  },
  {
    "id": 207,
    "start": "2013-07-20",
    "content": "質的変数の相関と因子分析",
    "title": "TokyoR#32",
    "misc": "https://web.archive.org/web/20140911201225/https://atnd.org/events/40213"
  },
  {
    "id": 208,
    "start": "2013-07-20",
    "content": "S言語拡張のアイデアと淘汰",
    "title": "TokyoR#32",
    "misc": "https://web.archive.org/web/20140911201225/https://atnd.org/events/40213"
  },
  {
    "id": 209,
    "start": "2013-07-20",
    "content": "RとC++と画像処理 (PART4)",
    "title": "TokyoR#32LT",
    "misc": "https://web.archive.org/web/20140911201225/https://atnd.org/events/40213"
  },
  {
    "id": 210,
    "start": "2013-07-20",
    "content": "サンプリングと推定(仮)",
    "title": "TokyoR#32LT",
    "misc": "https://web.archive.org/web/20140911201225/https://atnd.org/events/40213"
  },
  {
    "id": 211,
    "start": "2013-07-20",
    "content": "Rとオープンデータ(仮)",
    "title": "TokyoR#32LT",
    "misc": "https://web.archive.org/web/20140911201225/https://atnd.org/events/40213"
  },
  {
    "id": 212,
    "start": "2013-08-31",
    "content": "因子分析",
    "title": "TokyoR#33",
    "misc": "https://web.archive.org/web/20150925193804/https://atnd.org/events/42438"
  },
  {
    "id": 213,
    "start": "2013-08-31",
    "content": "ロジスティック回帰の考え方・使い方",
    "title": "TokyoR#33",
    "misc": "https://web.archive.org/web/20150925193804/https://atnd.org/events/42438"
  },
  {
    "id": 214,
    "start": "2013-08-31",
    "content": "Rで計量時系列分析~駆け足でCRANパッケージ総ざらい~",
    "title": "TokyoR#33",
    "misc": "https://web.archive.org/web/20150925193804/https://atnd.org/events/42438"
  },
  {
    "id": 215,
    "start": "2013-08-31",
    "content": "Rで項目反応理論、テキストマイニング、研修やってますという三題噺",
    "title": "TokyoR#33",
    "misc": "https://web.archive.org/web/20150925193804/https://atnd.org/events/42438"
  },
  {
    "id": 216,
    "start": "2013-08-31",
    "content": "21世紀の手法対決",
    "title": "TokyoR#33",
    "misc": "https://web.archive.org/web/20150925193804/https://atnd.org/events/42438"
  },
  {
    "id": 217,
    "start": "2013-08-31",
    "content": "位置情報アプリのチェックインデータを使った相関分析",
    "title": "TokyoR#33LT",
    "misc": "https://web.archive.org/web/20150925193804/https://atnd.org/events/42438"
  },
  {
    "id": 218,
    "start": "2013-08-31",
    "content": "僕がRを使って篠崎愛似の彼女を見つけるまで",
    "title": "TokyoR#33LT",
    "misc": "https://web.archive.org/web/20150925193804/https://atnd.org/events/42438"
  },
  {
    "id": 219,
    "start": "2013-08-31",
    "content": "RcppEigenと特異値分解",
    "title": "TokyoR#33LT",
    "misc": "https://web.archive.org/web/20150925193804/https://atnd.org/events/42438"
  },
  {
    "id": 220,
    "start": "2013-08-31",
    "content": "とある金融屋の統計技師が時系列解析してみた~To my dear wife, phoenix~",
    "title": "TokyoR#33LT",
    "misc": "https://web.archive.org/web/20150925193804/https://atnd.org/events/42438"
  },
  {
    "id": 221,
    "start": "2013-08-31",
    "content": "『データサイエンティストになれなかった皆さんへ(仮)』",
    "title": "TokyoR#33LT",
    "misc": "https://web.archive.org/web/20150925193804/https://atnd.org/events/42438"
  },
  {
    "id": 222,
    "start": "2013-08-31",
    "content": "相関係数と決定係数",
    "title": "TokyoR#33LT",
    "misc": "https://web.archive.org/web/20150925193804/https://atnd.org/events/42438"
  },
  {
    "id": 223,
    "start": "2013-08-31",
    "content": "機動戦士ガンダムのその後",
    "title": "TokyoR#33LT",
    "misc": "https://web.archive.org/web/20150925193804/https://atnd.org/events/42438"
  },
  {
    "id": 224,
    "start": "2013-08-31",
    "content": "R+python で KAGGLE2値予測に挑戦!",
    "title": "TokyoR#33LT",
    "misc": "https://web.archive.org/web/20150925193804/https://atnd.org/events/42438"
  },
  {
    "id": 225,
    "start": "2013-10-12",
    "content": "決定木",
    "title": "TokyoR#34",
    "misc": "https://web.archive.org/web/20150925224140/https://atnd.org/events/43885"
  },
  {
    "id": 226,
    "start": "2013-10-12",
    "content": "共分散構造分析",
    "title": "TokyoR#34",
    "misc": "https://web.archive.org/web/20150925224140/https://atnd.org/events/43885"
  },
  {
    "id": 227,
    "start": "2013-10-12",
    "content": "MCMCとかの理論的なところをRで例を見ながら的な",
    "title": "TokyoR#34",
    "misc": "https://web.archive.org/web/20150925224140/https://atnd.org/events/43885"
  },
  {
    "id": 228,
    "start": "2013-10-12",
    "content": "アクションマイニングによる最適アクションの導出",
    "title": "TokyoR#34",
    "misc": "https://web.archive.org/web/20150925224140/https://atnd.org/events/43885"
  },
  {
    "id": 229,
    "start": "2013-10-12",
    "content": "決定木を用いた、異性タイプの嗜好パターン分析",
    "title": "TokyoR#34LT",
    "misc": "https://web.archive.org/web/20150925224140/https://atnd.org/events/43885"
  },
  {
    "id": 230,
    "start": "2013-11-09",
    "content": "テキスト",
    "title": "TokyoR#35",
    "misc": "https://web.archive.org/web/20150925193818/https://atnd.org/events/45114"
  },
  {
    "id": 231,
    "start": "2013-11-09",
    "content": "Rユーザのための? Julia入門",
    "title": "TokyoR#35",
    "misc": "https://web.archive.org/web/20150925193818/https://atnd.org/events/45114"
  },
  {
    "id": 232,
    "start": "2013-11-09",
    "content": "data.tableパッケージで大規模データをサクッと処理する",
    "title": "TokyoR#35",
    "misc": "https://web.archive.org/web/20150925193818/https://atnd.org/events/45114"
  },
  {
    "id": 233,
    "start": "2013-11-09",
    "content": "Rでネットワーク解析とGIS",
    "title": "TokyoR#35",
    "misc": "https://web.archive.org/web/20150925193818/https://atnd.org/events/45114"
  },
  {
    "id": 234,
    "start": "2013-11-09",
    "content": "ロバスティーヌのお悩み",
    "title": "TokyoR#35LT",
    "misc": "https://web.archive.org/web/20150925193818/https://atnd.org/events/45114"
  },
  {
    "id": 235,
    "start": "2013-11-09",
    "content": "Multi-Armed-Bundit in R",
    "title": "TokyoR#35LT",
    "misc": "https://web.archive.org/web/20150925193818/https://atnd.org/events/45114"
  },
  {
    "id": 236,
    "start": "2013-11-09",
    "content": "5分でわかるベイズ確率",
    "title": "TokyoR#35LT",
    "misc": "https://web.archive.org/web/20150925193818/https://atnd.org/events/45114"
  },
  {
    "id": 237,
    "start": "2013-11-09",
    "content": "しゅうかつ",
    "title": "TokyoR#35LT",
    "misc": "https://web.archive.org/web/20150925193818/https://atnd.org/events/45114"
  },
  {
    "id": 238,
    "start": "2013-11-09",
    "content": "ソフトウェアジャパン2014の紹介",
    "title": "TokyoR#35LT",
    "misc": "https://web.archive.org/web/20150925193818/https://atnd.org/events/45114"
  },
  {
    "id": 239,
    "start": "2013-11-09",
    "content": "R Advent Calendar 2013 のご案内",
    "title": "TokyoR#35LT",
    "misc": "https://web.archive.org/web/20150925193818/https://atnd.org/events/45114"
  },
  {
    "id": 240,
    "start": "2013-11-09",
    "content": "西内まりやとセブンイレブンのドミナント戦略のKPIとVisualisationについて",
    "title": "TokyoR#35LT",
    "misc": "https://web.archive.org/web/20150925193818/https://atnd.org/events/45114"
  },
  {
    "id": 241,
    "start": "2014-02-22",
    "content": "Rによるやさしい統計学 第20章 検定力分析によるサンプルサイズの決定",
    "title": "TokyoR#36",
    "misc": "https://web.archive.org/web/20140912045445/https://atnd.org/events/47713"
  },
  {
    "id": 242,
    "start": "2014-02-22",
    "content": "~knitrパッケージではじめる~『R MarkdownでReproducible Research』",
    "title": "TokyoR#36",
    "misc": "https://web.archive.org/web/20140912045445/https://atnd.org/events/47713"
  },
  {
    "id": 243,
    "start": "2014-02-22",
    "content": "RでSPADEとSNEを使って次元削減と可視化",
    "title": "TokyoR#36",
    "misc": "https://web.archive.org/web/20140912045445/https://atnd.org/events/47713"
  },
  {
    "id": 244,
    "start": "2014-02-22",
    "content": "Rで学ぶ離散選択モデル",
    "title": "TokyoR#36",
    "misc": "https://web.archive.org/web/20140912045445/https://atnd.org/events/47713"
  },
  {
    "id": 245,
    "start": "2014-02-22",
    "content": "EasyHTMLReportの紹介",
    "title": "TokyoR#36",
    "misc": "https://web.archive.org/web/20140912045445/https://atnd.org/events/47713"
  },
  {
    "id": 246,
    "start": "2014-02-22",
    "content": "dplyrパッケージ徹底解説",
    "title": "TokyoR#36LT",
    "misc": "https://web.archive.org/web/20140912045445/https://atnd.org/events/47713"
  },
  {
    "id": 247,
    "start": "2014-02-22",
    "content": "ゲームパラメータの決定方法",
    "title": "TokyoR#36LT",
    "misc": "https://web.archive.org/web/20140912045445/https://atnd.org/events/47713"
  },
  {
    "id": 248,
    "start": "2014-02-22",
    "content": "Rで部分空間法",
    "title": "TokyoR#36LT",
    "misc": "https://web.archive.org/web/20140912045445/https://atnd.org/events/47713"
  },
  {
    "id": 249,
    "start": "2014-02-22",
    "content": "Rと確率分布",
    "title": "TokyoR#36LT",
    "misc": "https://web.archive.org/web/20140912045445/https://atnd.org/events/47713"
  },
  {
    "id": 250,
    "start": "2014-02-22",
    "content": "RStan で作る人工データ",
    "title": "TokyoR#36LT",
    "misc": "https://web.archive.org/web/20140912045445/https://atnd.org/events/47713"
  },
  {
    "id": 251,
    "start": "2014-02-22",
    "content": "Rで見るサーモンの価格周期性",
    "title": "TokyoR#36LT",
    "misc": "https://web.archive.org/web/20140912045445/https://atnd.org/events/47713"
  },
  {
    "id": 252,
    "start": "2014-03-29",
    "content": "テキスト",
    "title": "TokyoR#37",
    "misc": "https://web.archive.org/web/20150925193828/https://atnd.org/events/48048"
  },
  {
    "id": 253,
    "start": "2014-03-29",
    "content": "Rによる特徴選択",
    "title": "TokyoR#37",
    "misc": "https://web.archive.org/web/20150925193828/https://atnd.org/events/48048"
  },
  {
    "id": 254,
    "start": "2014-03-29",
    "content": "Rで学ぶ離散選択モデル(リベンジ)",
    "title": "TokyoR#37",
    "misc": "https://web.archive.org/web/20150925193828/https://atnd.org/events/48048"
  },
  {
    "id": 255,
    "start": "2014-03-29",
    "content": "Rでお部屋探し",
    "title": "TokyoR#37",
    "misc": "https://web.archive.org/web/20150925193828/https://atnd.org/events/48048"
  },
  {
    "id": 256,
    "start": "2014-03-29",
    "content": "Rで分位点回帰",
    "title": "TokyoR#37LT",
    "misc": "https://web.archive.org/web/20150925193828/https://atnd.org/events/48048"
  },
  {
    "id": 257,
    "start": "2014-03-29",
    "content": "rchartsによるインタラクティブな可視化表現",
    "title": "TokyoR#37LT",
    "misc": "https://web.archive.org/web/20150925193828/https://atnd.org/events/48048"
  },
  {
    "id": 258,
    "start": "2014-03-29",
    "content": "ちょっと詳しい欠測データの補完",
    "title": "TokyoR#37LT",
    "misc": "https://web.archive.org/web/20150925193828/https://atnd.org/events/48048"
  },
  {
    "id": 259,
    "start": "2014-03-29",
    "content": "生物成長曲線予測の事例",
    "title": "TokyoR#37LT",
    "misc": "https://web.archive.org/web/20150925193828/https://atnd.org/events/48048"
  },
  {
    "id": 260,
    "start": "2014-03-29",
    "content": "暮らしの中のデータマイニング その1 〜初対面の人に会うとき〜",
    "title": "TokyoR#37LT",
    "misc": "https://web.archive.org/web/20150925193828/https://atnd.org/events/48048"
  },
  {
    "id": 261,
    "start": "2014-03-29",
    "content": "カーネルとSVM",
    "title": "TokyoR#37LT",
    "misc": "https://web.archive.org/web/20150925193828/https://atnd.org/events/48048"
  },
  {
    "id": 262,
    "start": "2014-04-19",
    "content": "パッケージの作り方",
    "title": "TokyoR#38",
    "misc": "https://web.archive.org/web/20150925193854/https://atnd.org/events/49186"
  },
  {
    "id": 263,
    "start": "2014-04-19",
    "content": "機械学習のモデル構築・評価について",
    "title": "TokyoR#38",
    "misc": "https://web.archive.org/web/20150925193854/https://atnd.org/events/49186"
  },
  {
    "id": 264,
    "start": "2014-04-19",
    "content": "状態空間モデルの考え方•使い方",
    "title": "TokyoR#38",
    "misc": "https://web.archive.org/web/20150925193854/https://atnd.org/events/49186"
  },
  {
    "id": 265,
    "start": "2014-04-19",
    "content": "100人のための統計解析 – 和食レストラン編",
    "title": "TokyoR#38",
    "misc": "https://web.archive.org/web/20150925193854/https://atnd.org/events/49186"
  },
  {
    "id": 266,
    "start": "2014-04-19",
    "content": "R で学ぶ関数型プログラミング",
    "title": "TokyoR#38",
    "misc": "https://web.archive.org/web/20150925193854/https://atnd.org/events/49186"
  },
  {
    "id": 267,
    "start": "2014-04-19",
    "content": "Rで野球のデータ解析がしたい",
    "title": "TokyoR#38LT",
    "misc": "https://web.archive.org/web/20150925193854/https://atnd.org/events/49186"
  },
  {
    "id": 268,
    "start": "2014-04-19",
    "content": "アンケート分析で、AICを自力でstepより改善してみた",
    "title": "TokyoR#38LT",
    "misc": "https://web.archive.org/web/20150925193854/https://atnd.org/events/49186"
  },
  {
    "id": 269,
    "start": "2014-04-19",
    "content": "某データ分析コンペサイトの話",
    "title": "TokyoR#38LT",
    "misc": "https://web.archive.org/web/20150925193854/https://atnd.org/events/49186"
  },
  {
    "id": 270,
    "start": "2014-05-31",
    "content": "Rで学ぶデータマイニングI 第14〜15章",
    "title": "TokyoR#39",
    "misc": "https://web.archive.org/web/20150925224212/https://atnd.org/events/50887"
  },
  {
    "id": 271,
    "start": "2014-05-31",
    "content": "(1)RStudioの日本語化(2)データサイエンスの研修やってます",
    "title": "TokyoR#39",
    "misc": "https://web.archive.org/web/20150925224212/https://atnd.org/events/50887"
  },
  {
    "id": 272,
    "start": "2014-05-31",
    "content": "Rで野球解析",
    "title": "TokyoR#39",
    "misc": "https://web.archive.org/web/20150925224212/https://atnd.org/events/50887"
  },
  {
    "id": 273,
    "start": "2014-05-31",
    "content": "Excelで集計分析",
    "title": "TokyoR#39",
    "misc": "https://web.archive.org/web/20150925224212/https://atnd.org/events/50887"
  },
  {
    "id": 274,
    "start": "2014-05-31",
    "content": "Rと地図(とベイズ)のお話",
    "title": "TokyoR#39",
    "misc": "https://web.archive.org/web/20150925224212/https://atnd.org/events/50887"
  },
  {
    "id": 275,
    "start": "2014-05-31",
    "content": "Devium を使ったヒト血清中化学物質の解析",
    "title": "TokyoR#39",
    "misc": "https://web.archive.org/web/20150925224212/https://atnd.org/events/50887"
  },
  {
    "id": 276,
    "start": "2014-05-31",
    "content": "お前の逐モン、GETだぜ!",
    "title": "TokyoR#39LT",
    "misc": "https://web.archive.org/web/20150925224212/https://atnd.org/events/50887"
  },
  {
    "id": 277,
    "start": "2014-05-31",
    "content": "Rでダイエット",
    "title": "TokyoR#39LT",
    "misc": "https://web.archive.org/web/20150925224212/https://atnd.org/events/50887"
  },
  {
    "id": 278,
    "start": "2014-05-31",
    "content": "家に早く帰りたい",
    "title": "TokyoR#39LT",
    "misc": "https://web.archive.org/web/20150925224212/https://atnd.org/events/50887"
  },
  {
    "id": 279,
    "start": "2014-05-31",
    "content": "RとJulia(仮)",
    "title": "TokyoR#39LT",
    "misc": "https://web.archive.org/web/20150925224212/https://atnd.org/events/50887"
  },
  {
    "id": 280,
    "start": "2014-05-31",
    "content": "高速で前処理するNYSOL",
    "title": "TokyoR#39LT",
    "misc": "https://web.archive.org/web/20150925224212/https://atnd.org/events/50887"
  },
  {
    "id": 281,
    "start": "2014-06-14",
    "content": "Rで学ぶデータマイニングI 第16章",
    "title": "TokyoR#40",
    "misc": "https://web.archive.org/web/20150919082848/https://atnd.org/events/51779"
  },
  {
    "id": 282,
    "start": "2014-06-14",
    "content": "ハイブリッド型樹木法",
    "title": "TokyoR#40",
    "misc": "https://web.archive.org/web/20150919082848/https://atnd.org/events/51779"
  },
  {
    "id": 283,
    "start": "2014-06-14",
    "content": "動学的パネルデータ分析",
    "title": "TokyoR#40",
    "misc": "https://web.archive.org/web/20150919082848/https://atnd.org/events/51779"
  },
  {
    "id": 284,
    "start": "2014-06-14",
    "content": "独立成分分析",
    "title": "TokyoR#40",
    "misc": "https://web.archive.org/web/20150919082848/https://atnd.org/events/51779"
  },
  {
    "id": 285,
    "start": "2014-06-14",
    "content": "おとうさんでもできます",
    "title": "TokyoR#40LT",
    "misc": "https://web.archive.org/web/20150919082848/https://atnd.org/events/51779"
  },
  {
    "id": 286,
    "start": "2014-06-14",
    "content": "RでExperience APIをいじる",
    "title": "TokyoR#40LT",
    "misc": "https://web.archive.org/web/20150919082848/https://atnd.org/events/51779"
  },
  {
    "id": 287,
    "start": "2014-06-14",
    "content": "socceR!",
    "title": "TokyoR#40LT",
    "misc": "https://web.archive.org/web/20150919082848/https://atnd.org/events/51779"
  },
  {
    "id": 288,
    "start": "2014-07-12",
    "content": "Rで学ぶデータマイニングI 第17章",
    "title": "TokyoR#41",
    "misc": "https://web.archive.org/web/20150924233402/https://atnd.org/events/52749"
  },
  {
    "id": 289,
    "start": "2014-07-12",
    "content": "Rパッケージ作成",
    "title": "TokyoR#41",
    "misc": "https://web.archive.org/web/20150924233402/https://atnd.org/events/52749"
  },
  {
    "id": 290,
    "start": "2014-07-12",
    "content": "I/Oについて ~ミスマッチを減らせ!~",
    "title": "TokyoR#41",
    "misc": "https://web.archive.org/web/20150924233402/https://atnd.org/events/52749"
  },
  {
    "id": 291,
    "start": "2014-07-12",
    "content": "サポートベクターマシン入門 〜オブジェクト自動識別システムの構築〜",
    "title": "TokyoR#41",
    "misc": "https://web.archive.org/web/20150924233402/https://atnd.org/events/52749"
  },
  {
    "id": 292,
    "start": "2014-07-12",
    "content": "Yokohama.Rはじめますた",
    "title": "TokyoR#41LT",
    "misc": "https://web.archive.org/web/20150924233402/https://atnd.org/events/52749"
  },
  {
    "id": 293,
    "start": "2014-07-12",
    "content": "久しぶりのISM",
    "title": "TokyoR#41LT",
    "misc": "https://web.archive.org/web/20150924233402/https://atnd.org/events/52749"
  },
  {
    "id": 294,
    "start": "2014-07-12",
    "content": "UseR!2014@LA",
    "title": "TokyoR#41LT",
    "misc": "https://web.archive.org/web/20150924233402/https://atnd.org/events/52749"
  },
  {
    "id": 295,
    "start": "2014-08-30",
    "content": "導入セッション 2 データの可視化(ggplot2)",
    "title": "TokyoR#42",
    "misc": "https://web.archive.org/web/20150925231315/https://atnd.org/events/54680"
  },
  {
    "id": 296,
    "start": "2014-08-30",
    "content": "Rで学ぶデータマイニングI 第18章",
    "title": "TokyoR#42",
    "misc": "https://web.archive.org/web/20150925231315/https://atnd.org/events/54680"
  },
  {
    "id": 297,
    "start": "2014-08-30",
    "content": "はじめようテキスト自動要約",
    "title": "TokyoR#42",
    "misc": "https://web.archive.org/web/20150925231315/https://atnd.org/events/54680"
  },
  {
    "id": 298,
    "start": "2014-08-30",
    "content": "パッケージ作成法(RStudio編)",
    "title": "TokyoR#42",
    "misc": "https://web.archive.org/web/20150925231315/https://atnd.org/events/54680"
  },
  {
    "id": 299,
    "start": "2014-08-30",
    "content": "データハンドリング系の何か",
    "title": "TokyoR#42",
    "misc": "https://web.archive.org/web/20150925231315/https://atnd.org/events/54680"
  },
  {
    "id": 300,
    "start": "2014-08-30",
    "content": "Rの影について",
    "title": "TokyoR#42LT",
    "misc": "https://web.archive.org/web/20150925231315/https://atnd.org/events/54680"
  },
  {
    "id": 301,
    "start": "2014-08-30",
    "content": "Bokete Player の裏側",
    "title": "TokyoR#42LT",
    "misc": "https://web.archive.org/web/20150925231315/https://atnd.org/events/54680"
  },
  {
    "id": 302,
    "start": "2014-08-30",
    "content": "データサイエンティスト必見!M-1グランプリ",
    "title": "TokyoR#42LT",
    "misc": "https://web.archive.org/web/20150925231315/https://atnd.org/events/54680"
  },
  {
    "id": 303,
    "start": "2014-11-01",
    "content": "テキスト:セグメンテーション",
    "title": "TokyoR#44",
    "misc": "https://web.archive.org/web/20150925195344/https://atnd.org/events/57640"
  },
  {
    "id": 304,
    "start": "2014-11-01",
    "content": "シリーズ前処理2014 小綺麗なデータ作成",
    "title": "TokyoR#44",
    "misc": "https://web.archive.org/web/20150925195344/https://atnd.org/events/57640"
  },
  {
    "id": 305,
    "start": "2014-11-01",
    "content": "Jubatusつかってみたよ",
    "title": "TokyoR#44",
    "misc": "https://web.archive.org/web/20150925195344/https://atnd.org/events/57640"
  },
  {
    "id": 306,
    "start": "2014-11-01",
    "content": "シリーズ前処理2014 次元削減",
    "title": "TokyoR#44",
    "misc": "https://web.archive.org/web/20150925195344/https://atnd.org/events/57640"
  },
  {
    "id": 307,
    "start": "2014-11-01",
    "content": "RColorBrewerとcolorRampPalette()で地図描画",
    "title": "TokyoR#44LT",
    "misc": "https://web.archive.org/web/20150925195344/https://atnd.org/events/57640"
  },
  {
    "id": 308,
    "start": "2014-11-01",
    "content": "Rユーザーのためのmコマンド",
    "title": "TokyoR#44LT",
    "misc": "https://web.archive.org/web/20150925195344/https://atnd.org/events/57640"
  },
  {
    "id": 309,
    "start": "2014-11-01",
    "content": "ガチで理系な方に、その相関は間違ってます、と言われたマーケ女子の話",
    "title": "TokyoR#44LT",
    "misc": "https://web.archive.org/web/20150925195344/https://atnd.org/events/57640"
  },
  {
    "id": 310,
    "start": "2014-11-01",
    "content": "近況報告",
    "title": "TokyoR#44LT",
    "misc": "https://web.archive.org/web/20150925195344/https://atnd.org/events/57640"
  },
  {
    "id": 311,
    "start": "2014-11-01",
    "content": "この1年間を振り返って",
    "title": "TokyoR#44LT",
    "misc": "https://web.archive.org/web/20150925195344/https://atnd.org/events/57640"
  },
  {
    "id": 312,
    "start": "2014-11-01",
    "content": "これからのRとデータの話をしよう",
    "title": "TokyoR#44LT",
    "misc": "https://web.archive.org/web/20150925195344/https://atnd.org/events/57640"
  },
  {
    "id": 313,
    "start": "2015-01-17",
    "content": "Rによる回帰分析",
    "title": "TokyoR#45",
    "misc": "https://web.archive.org/web/20150918221501/https://atnd.org/events/60908"
  },
  {
    "id": 314,
    "start": "2015-01-17",
    "content": "2015 Rコトハジメ",
    "title": "TokyoR#45",
    "misc": "https://web.archive.org/web/20150918221501/https://atnd.org/events/60908"
  },
  {
    "id": 315,
    "start": "2015-01-17",
    "content": "シリーズ前処理20151",
    "title": "TokyoR#45",
    "misc": "https://web.archive.org/web/20150918221501/https://atnd.org/events/60908"
  },
  {
    "id": 316,
    "start": "2015-01-17",
    "content": "typedFunction ∼型情報で Rをスピードアップ",
    "title": "TokyoR#45",
    "misc": "https://web.archive.org/web/20150918221501/https://atnd.org/events/60908"
  },
  {
    "id": 317,
    "start": "2015-01-17",
    "content": "カーネル多変量解析 第2章 カーネル多変量解析の仕組み",
    "title": "TokyoR#45",
    "misc": "https://web.archive.org/web/20150918221501/https://atnd.org/events/60908"
  },
  {
    "id": 318,
    "start": "2015-01-17",
    "content": "Jenkins によるレポートスクリプト管理",
    "title": "TokyoR#45LT",
    "misc": "https://web.archive.org/web/20150918221501/https://atnd.org/events/60908"
  },
  {
    "id": 319,
    "start": "2015-01-17",
    "content": "巨人の勝率を上げるbot作りました",
    "title": "TokyoR#45LT",
    "misc": "https://web.archive.org/web/20150918221501/https://atnd.org/events/60908"
  },
  {
    "id": 320,
    "start": "2015-01-17",
    "content": "Shiny で確率分布を学ぶアプリ作った",
    "title": "TokyoR#45LT",
    "misc": "https://web.archive.org/web/20150918221501/https://atnd.org/events/60908"
  },
  {
    "id": 321,
    "start": "2015-01-17",
    "content": "分析で好みの娘をぶっこぬく",
    "title": "TokyoR#45LT",
    "misc": "https://web.archive.org/web/20150918221501/https://atnd.org/events/60908"
  },
  {
    "id": 322,
    "start": "2015-01-17",
    "content": "「R for Cloud Computing」",
    "title": "TokyoR#45LT",
    "misc": "https://web.archive.org/web/20150918221501/https://atnd.org/events/60908"
  },
  {
    "id": 323,
    "start": "2015-02-21",
    "content": "「使える大学・使えない大学」の事例から考えるアンケートの解析方法",
    "title": "TokyoR#46",
    "misc": "https://web.archive.org/web/20150925224246/https://atnd.org/events/61553"
  },
  {
    "id": 324,
    "start": "2015-02-21",
    "content": "Omitted variables in Logistic regression(仮)",
    "title": "TokyoR#47",
    "misc": "https://web.archive.org/web/20150925224246/https://atnd.org/events/61553"
  },
  {
    "id": 325,
    "start": "2015-02-21",
    "content": "htmlwidgetsでJavascriptの可視化をRに",
    "title": "TokyoR#48",
    "misc": "https://web.archive.org/web/20150925224246/https://atnd.org/events/61553"
  },
  {
    "id": 326,
    "start": "2015-02-21",
    "content": "cyREST入門~RとCytoscapeのAPI連携~",
    "title": "TokyoR#49",
    "misc": "https://web.archive.org/web/20150925224246/https://atnd.org/events/61553"
  },
  {
    "id": 327,
    "start": "2015-02-21",
    "content": "R6パッケージの紹介:機能と実装",
    "title": "TokyoR#50",
    "misc": "https://web.archive.org/web/20150925224246/https://atnd.org/events/61553"
  },
  {
    "id": 328,
    "start": "2015-02-21",
    "content": "ULT × 3",
    "title": "TokyoR#46LT",
    "misc": "https://web.archive.org/web/20150925224246/https://atnd.org/events/61553"
  },
  {
    "id": 329,
    "start": "2015-02-21",
    "content": "Japan.R補完計画",
    "title": "TokyoR#46LT",
    "misc": "https://web.archive.org/web/20150925224246/https://atnd.org/events/61553"
  },
  {
    "id": 330,
    "start": "2015-02-21",
    "content": "最強のハードディスクはどれだ?",
    "title": "TokyoR#46LT",
    "misc": "https://web.archive.org/web/20150925224246/https://atnd.org/events/61553"
  },
  {
    "id": 331,
    "start": "2015-02-21",
    "content": "俺とRとディリクレ分布",
    "title": "TokyoR#46LT",
    "misc": "https://web.archive.org/web/20150925224246/https://atnd.org/events/61553"
  },
  {
    "id": 332,
    "start": "2015-03-28",
    "content": "初心者セッション 1:10分で分かるR言語入門",
    "title": "TokyoR#47",
    "misc": "https://web.archive.org/web/20160618004959/http://atnd.org/events/63990"
  },
  {
    "id": 333,
    "start": "2015-03-28",
    "content": "初心者セッション2:続はじめてのR",
    "title": "TokyoR#47",
    "misc": "https://web.archive.org/web/20160618004959/http://atnd.org/events/63990"
  },
  {
    "id": 334,
    "start": "2015-03-28",
    "content": "uplit modellingを使ったDM最適化",
    "title": "TokyoR#47",
    "misc": "https://web.archive.org/web/20160618004959/http://atnd.org/events/63990"
  },
  {
    "id": 335,
    "start": "2015-03-28",
    "content": "形態素解析器 MeCab の新語・固有表現辞書 mecab-ipadic-neologd のご紹介とその応用例に関するデモ",
    "title": "TokyoR#47",
    "misc": "https://web.archive.org/web/20160618004959/http://atnd.org/events/63990"
  },
  {
    "id": 336,
    "start": "2015-06-20",
    "content": "Rを極めて個人的な意思決定に活かす",
    "title": "TokyoR#48",
    "misc": "https://web.archive.org/web/20150909233331/https://atnd.org/events/66469"
  },
  {
    "id": 337,
    "start": "2015-06-20",
    "content": "プログラミング言語Roop",
    "title": "TokyoR#48",
    "misc": "https://web.archive.org/web/20150909233331/https://atnd.org/events/66469"
  },
  {
    "id": 338,
    "start": "2015-06-20",
    "content": "RユーザのためのSpark入門",
    "title": "TokyoR#48",
    "misc": "https://web.archive.org/web/20150909233331/https://atnd.org/events/66469"
  },
  {
    "id": 339,
    "start": "2015-06-20",
    "content": "R のモデルの扱い方",
    "title": "TokyoR#48",
    "misc": "https://web.archive.org/web/20150909233331/https://atnd.org/events/66469"
  },
  {
    "id": 340,
    "start": "2015-06-20",
    "content": "俺のオジーがそんなにアホなわけがない(仮)",
    "title": "TokyoR#48LT",
    "misc": "https://web.archive.org/web/20150909233331/https://atnd.org/events/66469"
  },
  {
    "id": 341,
    "start": "2015-06-20",
    "content": "Github PagesでRPubsにサヨナラ!",
    "title": "TokyoR#48LT",
    "misc": "https://web.archive.org/web/20150909233331/https://atnd.org/events/66469"
  },
  {
    "id": 342,
    "start": "2015-06-20",
    "content": "R HTMLでドキュメントを作るのは間違っているのだろうか",
    "title": "TokyoR#48LT",
    "misc": "https://web.archive.org/web/20150909233331/https://atnd.org/events/66469"
  },
  {
    "id": 343,
    "start": "2015-06-20",
    "content": "1億5千万円欲しい (ロト6で遊ぶ)",
    "title": "TokyoR#48LT",
    "misc": "https://web.archive.org/web/20150909233331/https://atnd.org/events/66469"
  },
  {
    "id": 344,
    "start": "2015-06-20",
    "content": "R で簡単に並列処理が書ける pforeach パッケージ",
    "title": "TokyoR#48LT",
    "misc": "https://web.archive.org/web/20150909233331/https://atnd.org/events/66469"
  },
  {
    "id": 345,
    "start": "2015-06-20",
    "content": "規約にまつわるエトセトラ",
    "title": "TokyoR#48LT",
    "misc": "https://web.archive.org/web/20150909233331/https://atnd.org/events/66469"
  },
  {
    "id": 346,
    "start": "2015-06-20",
    "content": "『glmnet』の使い方",
    "title": "TokyoR#48LT",
    "misc": "https://web.archive.org/web/20150909233331/https://atnd.org/events/66469"
  },
  {
    "id": 347,
    "start": "2015-06-20",
    "content": "代謝解析練習用データUpした",
    "title": "TokyoR#48LT",
    "misc": "https://web.archive.org/web/20150909233331/https://atnd.org/events/66469"
  },
  {
    "id": 348,
    "start": "2015-06-20",
    "content": "Rによる特徴抽出",
    "title": "TokyoR#48LT",
    "misc": "https://web.archive.org/web/20150909233331/https://atnd.org/events/66469"
  },
  {
    "id": 349,
    "start": "2015-10-10",
    "content": "初心者セッション 1:10分でわかるR言語入門",
    "title": "TokyoR#51",
    "misc": "https://web.archive.org/web/20180622165401/https://atnd.org/events/70522"
  },
  {
    "id": 350,
    "start": "2015-10-10",
    "content": "初心者セッション3:インタラクティブな可視化",
    "title": "TokyoR#51",
    "misc": "https://web.archive.org/web/20180622165401/https://atnd.org/events/70522"
  },
  {
    "id": 351,
    "start": "2015-10-10",
    "content": "イチローvs松井、どっちが凄いか調べてみた",
    "title": "TokyoR#51",
    "misc": "https://web.archive.org/web/20180622165401/https://atnd.org/events/70522"
  },
  {
    "id": 352,
    "start": "2015-10-10",
    "content": "rstanで実装するマルコフスイッチング",
    "title": "TokyoR#51LT",
    "misc": "https://web.archive.org/web/20180622165401/https://atnd.org/events/70522"
  },
  {
    "id": 353,
    "start": "2016-04-30",
    "content": "実務でもきっと役立つ統計的因果推論",
    "title": "TokyoR#53",
    "misc": "https://web.archive.org/web/20190329175329/https://atnd.org/events/76648"
  },
  {
    "id": 354,
    "start": "2016-04-30",
    "content": "ハドリーさん、進捗どうですか?」(仮)",
    "title": "TokyoR#53",
    "misc": "https://web.archive.org/web/20190329175329/https://atnd.org/events/76648"
  },
  {
    "id": 355,
    "start": "2016-04-30",
    "content": "『実験計画 or クロス表のベイズ分析』",
    "title": "TokyoR#53",
    "misc": "https://web.archive.org/web/20190329175329/https://atnd.org/events/76648"
  },
  {
    "id": 356,
    "start": "2016-04-30",
    "content": "Rでやってみた金融テキストマイニング",
    "title": "TokyoR#53LT",
    "misc": "https://web.archive.org/web/20190329175329/https://atnd.org/events/76648"
  },
  {
    "id": 357,
    "start": "2016-04-30",
    "content": "R Markdownのちょいネタ集",
    "title": "TokyoR#53LT",
    "misc": "https://web.archive.org/web/20190329175329/https://atnd.org/events/76648"
  },
  {
    "id": 358,
    "start": "2016-04-30",
    "content": "mxnetで回帰",
    "title": "TokyoR#53LT",
    "misc": "https://web.archive.org/web/20190329175329/https://atnd.org/events/76648"
  },
  {
    "id": 359,
    "start": "2016-04-30",
    "content": "dplyrとは何だったのか",
    "title": "TokyoR#53LT",
    "misc": "https://web.archive.org/web/20190329175329/https://atnd.org/events/76648"
  },
  {
    "id": 360,
    "start": "2016-04-30",
    "content": "解約リストと分析と現場",
    "title": "TokyoR#53LT",
    "misc": "https://web.archive.org/web/20190329175329/https://atnd.org/events/76648"
  },
  {
    "id": 361,
    "start": "2016-06-19",
    "content": "2016年上半期版データマエショリスト入門",
    "title": "TokyoR#54",
    "misc": "https://web.archive.org/web/20190329221536/https://atnd.org/events/77861"
  },
  {
    "id": 362,
    "start": "2016-06-19",
    "content": "Datascience for me(仮)",
    "title": "TokyoR#54",
    "misc": "https://web.archive.org/web/20190329221536/https://atnd.org/events/77861"
  },
  {
    "id": 363,
    "start": "2016-06-19",
    "content": "Rで(当たらない)競馬予想をやってみた",
    "title": "TokyoR#54",
    "misc": "https://web.archive.org/web/20190329221536/https://atnd.org/events/77861"
  },
  {
    "id": 364,
    "start": "2016-07-30",
    "content": "初心者セッション2:GUIでらくらくRデータ解析",
    "title": "TokyoR#55",
    "misc": "https://web.archive.org/web/20190329222741/https://atnd.org/events/79586"
  },
  {
    "id": 365,
    "start": "2016-07-30",
    "content": "可視化周辺の進化がヤヴァイ 2016 〜Plotlyを中心として〜",
    "title": "TokyoR#55",
    "misc": "https://web.archive.org/web/20190329222741/https://atnd.org/events/79586"
  },
  {
    "id": 366,
    "start": "2016-07-30",
    "content": "実行環境について",
    "title": "TokyoR#55",
    "misc": "https://web.archive.org/web/20190329222741/https://atnd.org/events/79586"
  },
  {
    "id": 367,
    "start": "2016-07-30",
    "content": "RStudioでRnotebook機能を使ってみる",
    "title": "TokyoR#55LT",
    "misc": "https://web.archive.org/web/20190329222741/https://atnd.org/events/79586"
  },
  {
    "id": 368,
    "start": "2016-07-30",
    "content": "randomForestで感度分析",
    "title": "TokyoR#55LT",
    "misc": "https://web.archive.org/web/20190329222741/https://atnd.org/events/79586"
  },
  {
    "id": 369,
    "start": "2016-07-30",
    "content": "RMeCabと正規表現",
    "title": "TokyoR#55LT",
    "misc": "https://web.archive.org/web/20190329222741/https://atnd.org/events/79586"
  },
  {
    "id": 370,
    "start": "2016-07-30",
    "content": "ドラえもんでわかる統計的因果推論",
    "title": "TokyoR#55LT",
    "misc": "https://web.archive.org/web/20190329222741/https://atnd.org/events/79586"
  },
  {
    "id": 371,
    "start": "2016-07-30",
    "content": "SVMで欧州サッカーリーグの試合結果予測",
    "title": "TokyoR#55LT",
    "misc": "https://web.archive.org/web/20190329222741/https://atnd.org/events/79586"
  },
  {
    "id": 372,
    "start": "2016-07-30",
    "content": "日てれ サル語講座1",
    "title": "TokyoR#55LT",
    "misc": "https://web.archive.org/web/20190329222741/https://atnd.org/events/79586"
  },
  {
    "id": 373,
    "start": "2016-08-20",
    "content": "あまぁ〜い Rcpp 生活",
    "title": "TokyoR#56",
    "misc": "https://web.archive.org/web/20190329162941/https://atnd.org/events/80416"
  },
  {
    "id": 374,
    "start": "2016-08-20",
    "content": "installrパッケージで簡単R環境構築",
    "title": "TokyoR#56",
    "misc": "https://web.archive.org/web/20190329162941/https://atnd.org/events/80416"
  },
  {
    "id": 375,
    "start": "2016-08-20",
    "content": "甘さを抑えたRcpp",
    "title": "TokyoR#56LT",
    "misc": "https://web.archive.org/web/20190329162941/https://atnd.org/events/80416"
  },
  {
    "id": 376,
    "start": "2016-08-20",
    "content": "Rcppが支えるパッケージ",
    "title": "TokyoR#56LT",
    "misc": "https://web.archive.org/web/20190329162941/https://atnd.org/events/80416"
  },
  {
    "id": 377,
    "start": "2016-08-20",
    "content": "匿名バイナリ配布集団rwinlibについて",
    "title": "TokyoR#56LT",
    "misc": "https://web.archive.org/web/20190329162941/https://atnd.org/events/80416"
  },
  {
    "id": 378,
    "start": "2016-09-24",
    "content": "RとStanでクラウドセットアップ時間を分析してみたら",
    "title": "TokyoR#57",
    "misc": "https://web.archive.org/web/20190329190958/https://atnd.org/events/81471"
  },
  {
    "id": 379,
    "start": "2017-01-21",
    "content": "因果推論と個人情報と欠測補完のお話",
    "title": "TokyoR#58",
    "misc": "https://web.archive.org/web/20190329213015/https://atnd.org/events/84839"
  },
  {
    "id": 380,
    "start": "2017-01-21",
    "content": "マイニングのデータをマイニングしてみた",
    "title": "TokyoR#58",
    "misc": "https://web.archive.org/web/20190329213015/https://atnd.org/events/84839"
  },
  {
    "id": 381,
    "start": "2017-01-21",
    "content": "野良ビッグデータへの誘い",
    "title": "TokyoR#58",
    "misc": "https://web.archive.org/web/20190329213015/https://atnd.org/events/84839"
  },
  {
    "id": 382,
    "start": "2017-01-21",
    "content": "高次元データにおけるun-biased Average Treatment Effects の推定",
    "title": "TokyoR#58",
    "misc": "https://web.archive.org/web/20190329213015/https://atnd.org/events/84839"
  },
  {
    "id": 383,
    "start": "2017-01-21",
    "content": "Finding Alternate Features in Lassos with R",
    "title": "TokyoR#58LT",
    "misc": "https://web.archive.org/web/20190329213015/https://atnd.org/events/84839"
  },
  {
    "id": 384,
    "start": "2017-01-21",
    "content": "RとGeoJsonを用いた地理的分析の可視化",
    "title": "TokyoR#58LT",
    "misc": "https://web.archive.org/web/20190329213015/https://atnd.org/events/84839"
  },
  {
    "id": 385,
    "start": "2017-01-21",
    "content": "ソフトウェアジャパンの紹介",
    "title": "TokyoR#58LT",
    "misc": "https://web.archive.org/web/20190329213015/https://atnd.org/events/84839"
  },
  {
    "id": 386,
    "start": "2017-01-21",
    "content": "どきどき de R",
    "title": "TokyoR#58LT",
    "misc": "https://web.archive.org/web/20190329213015/https://atnd.org/events/84839"
  },
  {
    "id": 387,
    "start": "2017-03-18",
    "content": "ウェブAPIのためのRパッケージ作成の勘所(仮)",
    "title": "TokyoR#59",
    "misc": "https://web.archive.org/web/20190329211233/https://atnd.org/events/86528"
  },
  {
    "id": 388,
    "start": "2017-03-18",
    "content": "mlrパッケージによる機械学習実践入門",
    "title": "TokyoR#59LT",
    "misc": "https://web.archive.org/web/20190329211233/https://atnd.org/events/86528"
  },
  {
    "id": 389,
    "start": "2017-03-18",
    "content": "factorと和解せよ",
    "title": "TokyoR#59LT",
    "misc": "https://web.archive.org/web/20190329211233/https://atnd.org/events/86528"
  },
  {
    "id": 390,
    "start": "2017-03-18",
    "content": "fukuoka.R#07のお知らせと福岡在住2ヶ月のdoradora09が感じた福岡の分析事情",
    "title": "TokyoR#59LT",
    "misc": "https://web.archive.org/web/20190329211233/https://atnd.org/events/86528"
  },
  {
    "id": 391,
    "start": "2017-03-18",
    "content": "パッケージ作った(仮)",
    "title": "TokyoR#59LT",
    "misc": "https://web.archive.org/web/20190329211233/https://atnd.org/events/86528"
  },
  {
    "id": 392,
    "start": "2017-03-18",
    "content": "5分でできる範囲で確率分布入門のための確率入門",
    "title": "TokyoR#59LT",
    "misc": "https://web.archive.org/web/20190329211233/https://atnd.org/events/86528"
  },
  {
    "id": 393,
    "start": "2017-03-18",
    "content": "メタアナリシスの階層ベイズモデル",
    "title": "TokyoR#59LT",
    "misc": "https://web.archive.org/web/20190329211233/https://atnd.org/events/86528"
  },
  {
    "id": 394,
    "start": "2017-04-22",
    "content": "dplyr再入門",
    "title": "TokyoR#60",
    "misc": "https://web.archive.org/web/20190329164815/https://atnd.org/events/87238"
  },
  {
    "id": 395,
    "start": "2017-04-22",
    "content": "Rでendogenous stratification",
    "title": "TokyoR#60",
    "misc": "https://web.archive.org/web/20190329164815/https://atnd.org/events/87238"
  },
  {
    "id": 396,
    "start": "2017-04-22",
    "content": "ガンマ分布の最尤推定法について",
    "title": "TokyoR#60",
    "misc": "https://web.archive.org/web/20190329164815/https://atnd.org/events/87238"
  },
  {
    "id": 397,
    "start": "2017-04-22",
    "content": "クラスター分析におけるクラスタ数の決め方",
    "title": "TokyoR#60LT",
    "misc": "https://web.archive.org/web/20190329164815/https://atnd.org/events/87238"
  },
  {
    "id": 398,
    "start": "2017-04-22",
    "content": "rPrefパッケージでパレート非優越ソートとデータ抽出",
    "title": "TokyoR#60LT",
    "misc": "https://web.archive.org/web/20190329164815/https://atnd.org/events/87238"
  },
  {
    "id": 399,
    "start": "2017-04-22",
    "content": "男心をくすぐる女の戦略.R",
    "title": "TokyoR#60LT",
    "misc": "https://web.archive.org/web/20190329164815/https://atnd.org/events/87238"
  },
  {
    "id": 400,
    "start": "2017-04-22",
    "content": "DockerでMeCabの環境構築",
    "title": "TokyoR#60LT",
    "misc": "https://web.archive.org/web/20190329164815/https://atnd.org/events/87238"
  },
  {
    "id": 401,
    "start": "2017-05-20",
    "content": "Rでダッシュボード開発",
    "title": "TokyoR#61",
    "misc": "https://web.archive.org/web/20190329190955/https://atnd.org/events/87878"
  },
  {
    "id": 402,
    "start": "2017-05-20",
    "content": "RMarkdownの内部とテンプレート開発について",
    "title": "TokyoR#61",
    "misc": "https://web.archive.org/web/20190329190955/https://atnd.org/events/87878"
  },
  {
    "id": 403,
    "start": "2017-05-20",
    "content": "RとApache OpenNLPではじめる自然言語処理",
    "title": "TokyoR#61LT",
    "misc": "https://web.archive.org/web/20190329190955/https://atnd.org/events/87878"
  },
  {
    "id": 404,
    "start": "2017-05-20",
    "content": "サバイバル分析によるユーザーのリテンション分析",
    "title": "TokyoR#61LT",
    "misc": "https://web.archive.org/web/20190329190955/https://atnd.org/events/87878"
  },
  {
    "id": 405,
    "start": "2017-05-20",
    "content": "AJAXサイトの情報をWebスクレイピング",
    "title": "TokyoR#61LT",
    "misc": "https://web.archive.org/web/20190329190955/https://atnd.org/events/87878"
  },
  {
    "id": 406,
    "start": "2017-06-24",
    "content": "R言語とデータマイニング基礎",
    "title": "TokyoR#62",
    "misc": "https://web.archive.org/web/20190329202713/https://atnd.org/events/88767"
  },
  {
    "id": 407,
    "start": "2017-06-24",
    "content": "整然データってなに?",
    "title": "TokyoR#62",
    "misc": "https://web.archive.org/web/20190329202713/https://atnd.org/events/88767"
  },
  {
    "id": 408,
    "start": "2017-06-24",
    "content": "mxnetで系列パターンマイニング",
    "title": "TokyoR#62",
    "misc": "https://web.archive.org/web/20190329202713/https://atnd.org/events/88767"
  },
  {
    "id": 409,
    "start": "2017-06-24",
    "content": "doAzureParallelでお手軽クラウド並列処理",
    "title": "TokyoR#62",
    "misc": "https://web.archive.org/web/20190329202713/https://atnd.org/events/88767"
  },
  {
    "id": 410,
    "start": "2017-06-24",
    "content": "Amazonで自分の名前を検索したらヒットするようになった話",
    "title": "TokyoR#62LT",
    "misc": "https://web.archive.org/web/20190329202713/https://atnd.org/events/88767"
  },
  {
    "id": 411,
    "start": "2017-06-24",
    "content": "自分マイニングをしよう",
    "title": "TokyoR#62LT",
    "misc": "https://web.archive.org/web/20190329202713/https://atnd.org/events/88767"
  },
  {
    "id": 412,
    "start": "2017-06-24",
    "content": "webshotパッケージでWebをキャプチャ",
    "title": "TokyoR#62LT",
    "misc": "https://web.archive.org/web/20190329202713/https://atnd.org/events/88767"
  },
  {
    "id": 413,
    "start": "2017-06-24",
    "content": "word prediction",
    "title": "TokyoR#62LT",
    "misc": "https://web.archive.org/web/20190329202713/https://atnd.org/events/88767"
  },
  {
    "id": 414,
    "start": "2017-07-22",
    "content": "R言語とデータマイニング基礎",
    "title": "TokyoR#63",
    "misc": "https://web.archive.org/web/20190329224341/https://atnd.org/events/89482"
  },
  {
    "id": 415,
    "start": "2017-07-22",
    "content": "Prophet入門 Facebookの予測システム【R編】",
    "title": "TokyoR#63",
    "misc": "https://web.archive.org/web/20190329224341/https://atnd.org/events/89482"
  },
  {
    "id": 416,
    "start": "2017-07-22",
    "content": "Rを用いたLife Time Valueの推定",
    "title": "TokyoR#63",
    "misc": "https://web.archive.org/web/20190329224341/https://atnd.org/events/89482"
  },
  {
    "id": 417,
    "start": "2017-07-22",
    "content": "これからはじめるShiny」(仮)",
    "title": "TokyoR#63",
    "misc": "https://web.archive.org/web/20190329224341/https://atnd.org/events/89482"
  },
  {
    "id": 418,
    "start": "2017-07-22",
    "content": "Rによるword2vec",
    "title": "TokyoR#63LT",
    "misc": "https://web.archive.org/web/20190329224341/https://atnd.org/events/89482"
  },
  {
    "id": 419,
    "start": "2017-07-22",
    "content": "気温が高い=暑い?",
    "title": "TokyoR#63LT",
    "misc": "https://web.archive.org/web/20190329224341/https://atnd.org/events/89482"
  },
  {
    "id": 420,
    "start": "2017-07-22",
    "content": "新卒採用を、まっとうに。 ーグループディスカッション評価の適正化ー",
    "title": "TokyoR#63LT",
    "misc": "https://web.archive.org/web/20190329224341/https://atnd.org/events/89482"
  },
  {
    "id": 421,
    "start": "2017-08-26",
    "content": "R言語とデータマイニング基礎",
    "title": "TokyoR#64",
    "misc": "https://web.archive.org/web/20190329222616/https://atnd.org/events/89814"
  },
  {
    "id": 422,
    "start": "2017-08-26",
    "content": "空間統計を使って地価分布図を描いてみる",
    "title": "TokyoR#64",
    "misc": "https://web.archive.org/web/20190329222616/https://atnd.org/events/89814"
  },
  {
    "id": 423,
    "start": "2017-08-26",
    "content": "Rによる日本語テキスト前処理(形態素解析を中心に)",
    "title": "TokyoR#64",
    "misc": "https://web.archive.org/web/20190329222616/https://atnd.org/events/89814"
  },
  {
    "id": 424,
    "start": "2017-08-26",
    "content": "Rからmidiファイルを読んでplotしてみたお話",
    "title": "TokyoR#64LT",
    "misc": "https://web.archive.org/web/20190329222616/https://atnd.org/events/89814"
  },
  {
    "id": 425,
    "start": "2017-08-26",
    "content": "R markdownで図表番号の自動付与と参照",
    "title": "TokyoR#64LT",
    "misc": "https://web.archive.org/web/20190329222616/https://atnd.org/events/89814"
  },
  {
    "id": 426,
    "start": "2017-08-26",
    "content": "コンテナで暮らそう",
    "title": "TokyoR#64LT",
    "misc": "https://web.archive.org/web/20190329222616/https://atnd.org/events/89814"
  },
  {
    "id": 427,
    "start": "2017-08-26",
    "content": "Fukuoka.R",
    "title": "TokyoR#64LT",
    "misc": "https://web.archive.org/web/20190329222616/https://atnd.org/events/89814"
  },
  {
    "id": 428,
    "start": "2017-08-26",
    "content": "KaggleのKernelsで学ぶデータのレポーティング技術",
    "title": "TokyoR#64LT",
    "misc": "https://web.archive.org/web/20190329222616/https://atnd.org/events/89814"
  },
  {
    "id": 429,
    "start": "2017-09-23",
    "content": "R言語とデータマイニング基礎",
    "title": "TokyoR#65",
    "misc": "https://web.archive.org/web/20190330001851/https://atnd.org/events/90837"
  },
  {
    "id": 430,
    "start": "2017-12-16",
    "content": "彼女に振られないための変化検知入門",
    "title": "TokyoR#66",
    "misc": "https://web.archive.org/web/20190330015211/https://atnd.org/events/92993"
  },
  {
    "id": 431,
    "start": "2017-12-16",
    "content": "flexdashboard本格入門",
    "title": "TokyoR#66",
    "misc": "https://web.archive.org/web/20190330015211/https://atnd.org/events/92993"
  },
  {
    "id": 432,
    "start": "2017-12-16",
    "content": "そろそろ手をだすpurrr",
    "title": "TokyoR#66",
    "misc": "https://web.archive.org/web/20190330015211/https://atnd.org/events/92993"
  },
  {
    "id": 433,
    "start": "2017-12-16",
    "content": "Rtweetで妊婦ユーザーを探して、妊婦DBを作ろう",
    "title": "TokyoR#66LT",
    "misc": "https://web.archive.org/web/20190330015211/https://atnd.org/events/92993"
  },
  {
    "id": 434,
    "start": "2017-12-16",
    "content": "treemapでナイスビジュアライズ!",
    "title": "TokyoR#66LT",
    "misc": "https://web.archive.org/web/20190330015211/https://atnd.org/events/92993"
  },
  {
    "id": 435,
    "start": "2018-01-20",
    "content": "キカイガクシューの解釈可能性について",
    "title": "TokyoR#67",
    "misc": "https://web.archive.org/web/20180202224708/https://atnd.org/events/93829"
  },
  {
    "id": 436,
    "start": "2018-01-20",
    "content": "RからGoogleCloudVisionを使う",
    "title": "TokyoR#67",
    "misc": "https://web.archive.org/web/20180202224708/https://atnd.org/events/93829"
  },
  {
    "id": 437,
    "start": "2018-01-20",
    "content": "Rのメタプログラミング入門",
    "title": "TokyoR#67",
    "misc": "https://web.archive.org/web/20180202224708/https://atnd.org/events/93829"
  },
  {
    "id": 438,
    "start": "2018-01-20",
    "content": "feature tweaking の紹介(仮)",
    "title": "TokyoR#67LT",
    "misc": "https://web.archive.org/web/20180202224708/https://atnd.org/events/93829"
  },
  {
    "id": 439,
    "start": "2018-01-20",
    "content": "ランダムフォレストを使ったEDA・探索的分析",
    "title": "TokyoR#67LT",
    "misc": "https://web.archive.org/web/20180202224708/https://atnd.org/events/93829"
  },
  {
    "id": 440,
    "start": "2018-01-20",
    "content": "vcdその3",
    "title": "TokyoR#67LT",
    "misc": "https://web.archive.org/web/20180202224708/https://atnd.org/events/93829"
  },
  {
    "id": 441,
    "start": "2018-01-20",
    "content": "R MarkdownでPythonを書く",
    "title": "TokyoR#67LT",
    "misc": "https://web.archive.org/web/20180202224708/https://atnd.org/events/93829"
  },
  {
    "id": 442,
    "start": "2018-01-20",
    "content": "Apache Arrowから取り残されるR",
    "title": "TokyoR#67LT",
    "misc": "https://web.archive.org/web/20180202224708/https://atnd.org/events/93829"
  },
  {
    "id": 443,
    "start": "2018-01-20",
    "content": "佐渡島を見積もる",
    "title": "TokyoR#67LT",
    "misc": "https://web.archive.org/web/20180202224708/https://atnd.org/events/93829"
  },
  {
    "id": 444,
    "start": "2018-01-20",
    "content": "R Shiny 100本ノックの進捗",
    "title": "TokyoR#67LT",
    "misc": "https://web.archive.org/web/20180202224708/https://atnd.org/events/93829"
  }
]
